<PetHallowsTempInfos>
	<PetHallowsTempInfo TemplateId="101001" TemplateName="Light &amp; Dark Claymore" HallowType="1" Grades="1" NeedItemCount1="20" NeedItemCount2="0" PropertyDatas="0,0,0,0,0,0" SkillTempId="41210101" EquipPetSonTypes="11702,11703"/>
	<PetHallowsTempInfo TemplateId="101002" TemplateName="Light &amp; Dark Claymore" HallowType="1" Grades="2" NeedItemCount1="20" NeedItemCount2="0" PropertyDatas="500,500,500,3000,100,100" SkillTempId="41210101" EquipPetSonTypes="11702,11703"/>
	<PetHallowsTempInfo TemplateId="101003" TemplateName="Light &amp; Dark Claymore" HallowType="1" Grades="3" NeedItemCount1="20" NeedItemCount2="0" PropertyDatas="1000,1000,1000,6000,200,200" SkillTempId="41210101" EquipPetSonTypes="11702,11703"/>
	<PetHallowsTempInfo TemplateId="101004" TemplateName="Light &amp; Dark Claymore" HallowType="1" Grades="4" NeedItemCount1="20" NeedItemCount2="0" PropertyDatas="1500,1500,1500,9000,300,300" SkillTempId="41210101" EquipPetSonTypes="11702,11703"/>
	<PetHallowsTempInfo TemplateId="101005" TemplateName="Light &amp; Dark Claymore" HallowType="1" Grades="5" NeedItemCount1="20" NeedItemCount2="0" PropertyDatas="2000,2000,2000,12000,400,400" SkillTempId="41210101" EquipPetSonTypes="11702,11703"/>
	<PetHallowsTempInfo TemplateId="101006" TemplateName="Light &amp; Dark Claymore" HallowType="1" Grades="6" NeedItemCount1="40" NeedItemCount2="0" PropertyDatas="2800,2800,2800,16800,560,560" SkillTempId="41210101" EquipPetSonTypes="11702,11703"/>
	<PetHallowsTempInfo TemplateId="101007" TemplateName="Light &amp; Dark Claymore" HallowType="1" Grades="7" NeedItemCount1="40" NeedItemCount2="0" PropertyDatas="3600,3600,3600,21600,720,720" SkillTempId="41210101" EquipPetSonTypes="11702,11703"/>
	<PetHallowsTempInfo TemplateId="101008" TemplateName="Light &amp; Dark Claymore" HallowType="1" Grades="8" NeedItemCount1="40" NeedItemCount2="0" PropertyDatas="4400,4400,4400,26400,880,880" SkillTempId="41210101" EquipPetSonTypes="11702,11703"/>
	<PetHallowsTempInfo TemplateId="101009" TemplateName="Light &amp; Dark Claymore" HallowType="1" Grades="9" NeedItemCount1="40" NeedItemCount2="0" PropertyDatas="5200,5200,5200,31200,1040,1040" SkillTempId="41210101" EquipPetSonTypes="11702,11703"/>
	<PetHallowsTempInfo TemplateId="101010" TemplateName="Light &amp; Dark Claymore" HallowType="1" Grades="10" NeedItemCount1="0" NeedItemCount2="200" PropertyDatas="5200,5200,5200,31200,1040,1040" SkillTempId="41210201" EquipPetSonTypes="11702,11703"/>
	<PetHallowsTempInfo TemplateId="101011" TemplateName="Light &amp; Dark Claymore" HallowType="1" Grades="11" NeedItemCount1="60" NeedItemCount2="0" PropertyDatas="6300,6300,6300,37800,1260,1260" SkillTempId="41210201" EquipPetSonTypes="11702,11703"/>
	<PetHallowsTempInfo TemplateId="101012" TemplateName="Light &amp; Dark Claymore" HallowType="1" Grades="12" NeedItemCount1="60" NeedItemCount2="0" PropertyDatas="7400,7400,7400,44400,1480,1480" SkillTempId="41210201" EquipPetSonTypes="11702,11703"/>
	<PetHallowsTempInfo TemplateId="101013" TemplateName="Light &amp; Dark Claymore" HallowType="1" Grades="13" NeedItemCount1="60" NeedItemCount2="0" PropertyDatas="8500,8500,8500,51000,1700,1700" SkillTempId="41210201" EquipPetSonTypes="11702,11703"/>
	<PetHallowsTempInfo TemplateId="101014" TemplateName="Light &amp; Dark Claymore" HallowType="1" Grades="14" NeedItemCount1="60" NeedItemCount2="0" PropertyDatas="9600,9600,9600,57600,1920,1920" SkillTempId="41210201" EquipPetSonTypes="11702,11703"/>
	<PetHallowsTempInfo TemplateId="101015" TemplateName="Light &amp; Dark Claymore" HallowType="1" Grades="15" NeedItemCount1="60" NeedItemCount2="0" PropertyDatas="10700,10700,10700,64200,2140,2140" SkillTempId="41210201" EquipPetSonTypes="11702,11703"/>
	<PetHallowsTempInfo TemplateId="101016" TemplateName="Light &amp; Dark Claymore" HallowType="1" Grades="16" NeedItemCount1="80" NeedItemCount2="0" PropertyDatas="12100,12100,12100,72600,2420,2420" SkillTempId="41210201" EquipPetSonTypes="11702,11703"/>
	<PetHallowsTempInfo TemplateId="101017" TemplateName="Light &amp; Dark Claymore" HallowType="1" Grades="17" NeedItemCount1="80" NeedItemCount2="0" PropertyDatas="13500,13500,13500,81000,2700,2700" SkillTempId="41210201" EquipPetSonTypes="11702,11703"/>
	<PetHallowsTempInfo TemplateId="101018" TemplateName="Light &amp; Dark Claymore" HallowType="1" Grades="18" NeedItemCount1="80" NeedItemCount2="0" PropertyDatas="14900,14900,14900,89400,2980,2980" SkillTempId="41210201" EquipPetSonTypes="11702,11703"/>
	<PetHallowsTempInfo TemplateId="101019" TemplateName="Light &amp; Dark Claymore" HallowType="1" Grades="19" NeedItemCount1="80" NeedItemCount2="0" PropertyDatas="16300,16300,16300,97800,3260,3260" SkillTempId="41210201" EquipPetSonTypes="11702,11703"/>
	<PetHallowsTempInfo TemplateId="101020" TemplateName="Light &amp; Dark Claymore" HallowType="1" Grades="20" NeedItemCount1="0" NeedItemCount2="500" PropertyDatas="16300,16300,16300,97800,3260,3260" SkillTempId="41210301" EquipPetSonTypes="11702,11703"/>
	<PetHallowsTempInfo TemplateId="101021" TemplateName="Light &amp; Dark Claymore" HallowType="1" Grades="21" NeedItemCount1="100" NeedItemCount2="0" PropertyDatas="18000,18000,18000,108000,3600,3600" SkillTempId="41210301" EquipPetSonTypes="11702,11703"/>
	<PetHallowsTempInfo TemplateId="101022" TemplateName="Light &amp; Dark Claymore" HallowType="1" Grades="22" NeedItemCount1="100" NeedItemCount2="0" PropertyDatas="19700,19700,19700,118200,3940,3940" SkillTempId="41210301" EquipPetSonTypes="11702,11703"/>
	<PetHallowsTempInfo TemplateId="101023" TemplateName="Light &amp; Dark Claymore" HallowType="1" Grades="23" NeedItemCount1="100" NeedItemCount2="0" PropertyDatas="21400,21400,21400,128400,4280,4280" SkillTempId="41210301" EquipPetSonTypes="11702,11703"/>
	<PetHallowsTempInfo TemplateId="101024" TemplateName="Light &amp; Dark Claymore" HallowType="1" Grades="24" NeedItemCount1="100" NeedItemCount2="0" PropertyDatas="23100,23100,23100,138600,4620,4620" SkillTempId="41210301" EquipPetSonTypes="11702,11703"/>
	<PetHallowsTempInfo TemplateId="101025" TemplateName="Light &amp; Dark Claymore" HallowType="1" Grades="25" NeedItemCount1="100" NeedItemCount2="0" PropertyDatas="24800,24800,24800,148800,4960,4960" SkillTempId="41210301" EquipPetSonTypes="11702,11703"/>
	<PetHallowsTempInfo TemplateId="101026" TemplateName="Light &amp; Dark Claymore" HallowType="1" Grades="26" NeedItemCount1="150" NeedItemCount2="0" PropertyDatas="26800,26800,26800,160800,5360,5360" SkillTempId="41210301" EquipPetSonTypes="11702,11703"/>
	<PetHallowsTempInfo TemplateId="101027" TemplateName="Light &amp; Dark Claymore" HallowType="1" Grades="27" NeedItemCount1="150" NeedItemCount2="0" PropertyDatas="28800,28800,28800,172800,5760,5760" SkillTempId="41210301" EquipPetSonTypes="11702,11703"/>
	<PetHallowsTempInfo TemplateId="101028" TemplateName="Light &amp; Dark Claymore" HallowType="1" Grades="28" NeedItemCount1="150" NeedItemCount2="0" PropertyDatas="30800,30800,30800,184800,6160,6160" SkillTempId="41210301" EquipPetSonTypes="11702,11703"/>
	<PetHallowsTempInfo TemplateId="101029" TemplateName="Light &amp; Dark Claymore" HallowType="1" Grades="29" NeedItemCount1="150" NeedItemCount2="0" PropertyDatas="32800,32800,32800,196800,6560,6560" SkillTempId="41210301" EquipPetSonTypes="11702,11703"/>
	<PetHallowsTempInfo TemplateId="101030" TemplateName="Light &amp; Dark Claymore" HallowType="1" Grades="30" NeedItemCount1="0" NeedItemCount2="1000" PropertyDatas="32800,32800,32800,196800,6560,6560" SkillTempId="41210401" EquipPetSonTypes="11702,11703"/>
	<PetHallowsTempInfo TemplateId="101031" TemplateName="Light &amp; Dark Claymore" HallowType="1" Grades="31" NeedItemCount1="200" NeedItemCount2="0" PropertyDatas="35300,35300,35300,211800,7060,7060" SkillTempId="41210401" EquipPetSonTypes="11702,11703"/>
	<PetHallowsTempInfo TemplateId="101032" TemplateName="Light &amp; Dark Claymore" HallowType="1" Grades="32" NeedItemCount1="200" NeedItemCount2="0" PropertyDatas="37800,37800,37800,226800,7560,7560" SkillTempId="41210401" EquipPetSonTypes="11702,11703"/>
	<PetHallowsTempInfo TemplateId="101033" TemplateName="Light &amp; Dark Claymore" HallowType="1" Grades="33" NeedItemCount1="200" NeedItemCount2="0" PropertyDatas="40300,40300,40300,241800,8060,8060" SkillTempId="41210401" EquipPetSonTypes="11702,11703"/>
	<PetHallowsTempInfo TemplateId="101034" TemplateName="Light &amp; Dark Claymore" HallowType="1" Grades="34" NeedItemCount1="200" NeedItemCount2="0" PropertyDatas="42800,42800,42800,256800,8560,8560" SkillTempId="41210401" EquipPetSonTypes="11702,11703"/>
	<PetHallowsTempInfo TemplateId="101035" TemplateName="Light &amp; Dark Claymore" HallowType="1" Grades="35" NeedItemCount1="200" NeedItemCount2="0" PropertyDatas="45300,45300,45300,271800,9060,9060" SkillTempId="41210401" EquipPetSonTypes="11702,11703"/>
	<PetHallowsTempInfo TemplateId="101036" TemplateName="Light &amp; Dark Claymore" HallowType="1" Grades="36" NeedItemCount1="250" NeedItemCount2="0" PropertyDatas="48300,48300,48300,289800,9660,9660" SkillTempId="41210401" EquipPetSonTypes="11702,11703"/>
	<PetHallowsTempInfo TemplateId="101037" TemplateName="Light &amp; Dark Claymore" HallowType="1" Grades="37" NeedItemCount1="250" NeedItemCount2="0" PropertyDatas="51300,51300,51300,307800,10260,10260" SkillTempId="41210401" EquipPetSonTypes="11702,11703"/>
	<PetHallowsTempInfo TemplateId="101038" TemplateName="Light &amp; Dark Claymore" HallowType="1" Grades="38" NeedItemCount1="250" NeedItemCount2="0" PropertyDatas="54300,54300,54300,325800,10860,10860" SkillTempId="41210401" EquipPetSonTypes="11702,11703"/>
	<PetHallowsTempInfo TemplateId="101039" TemplateName="Light &amp; Dark Claymore" HallowType="1" Grades="39" NeedItemCount1="250" NeedItemCount2="0" PropertyDatas="57300,57300,57300,343800,11460,11460" SkillTempId="41210401" EquipPetSonTypes="11702,11703"/>
	<PetHallowsTempInfo TemplateId="101040" TemplateName="Light &amp; Dark Claymore" HallowType="1" Grades="40" NeedItemCount1="0" NeedItemCount2="1000" PropertyDatas="57300,57300,57300,343800,11460,11460" SkillTempId="41210501" EquipPetSonTypes="11702,11703"/>
	<PetHallowsTempInfo TemplateId="101041" TemplateName="Light &amp; Dark Claymore" HallowType="1" Grades="41" NeedItemCount1="300" NeedItemCount2="0" PropertyDatas="60800,60800,60800,364800,12160,12160" SkillTempId="41210501" EquipPetSonTypes="11702,11703"/>
	<PetHallowsTempInfo TemplateId="101042" TemplateName="Light &amp; Dark Claymore" HallowType="1" Grades="42" NeedItemCount1="300" NeedItemCount2="0" PropertyDatas="64300,64300,64300,385800,12860,12860" SkillTempId="41210501" EquipPetSonTypes="11702,11703"/>
	<PetHallowsTempInfo TemplateId="101043" TemplateName="Light &amp; Dark Claymore" HallowType="1" Grades="43" NeedItemCount1="300" NeedItemCount2="0" PropertyDatas="67800,67800,67800,406800,13560,13560" SkillTempId="41210501" EquipPetSonTypes="11702,11703"/>
	<PetHallowsTempInfo TemplateId="101044" TemplateName="Light &amp; Dark Claymore" HallowType="1" Grades="44" NeedItemCount1="300" NeedItemCount2="0" PropertyDatas="71300,71300,71300,427800,14260,14260" SkillTempId="41210501" EquipPetSonTypes="11702,11703"/>
	<PetHallowsTempInfo TemplateId="101045" TemplateName="Light &amp; Dark Claymore" HallowType="1" Grades="45" NeedItemCount1="300" NeedItemCount2="0" PropertyDatas="74800,74800,74800,448800,14960,14960" SkillTempId="41210501" EquipPetSonTypes="11702,11703"/>
	<PetHallowsTempInfo TemplateId="101046" TemplateName="Light &amp; Dark Claymore" HallowType="1" Grades="46" NeedItemCount1="350" NeedItemCount2="0" PropertyDatas="78800,78800,78800,472800,15760,15760" SkillTempId="41210501" EquipPetSonTypes="11702,11703"/>
	<PetHallowsTempInfo TemplateId="101047" TemplateName="Light &amp; Dark Claymore" HallowType="1" Grades="47" NeedItemCount1="350" NeedItemCount2="0" PropertyDatas="82800,82800,82800,496800,16560,16560" SkillTempId="41210501" EquipPetSonTypes="11702,11703"/>
	<PetHallowsTempInfo TemplateId="101048" TemplateName="Light &amp; Dark Claymore" HallowType="1" Grades="48" NeedItemCount1="350" NeedItemCount2="0" PropertyDatas="86800,86800,86800,520800,17360,17360" SkillTempId="41210501" EquipPetSonTypes="11702,11703"/>
	<PetHallowsTempInfo TemplateId="101049" TemplateName="Light &amp; Dark Claymore" HallowType="1" Grades="49" NeedItemCount1="350" NeedItemCount2="0" PropertyDatas="90800,90800,90800,544800,18160,18160" SkillTempId="41210501" EquipPetSonTypes="11702,11703"/>
	<PetHallowsTempInfo TemplateId="101050" TemplateName="Light &amp; Dark Claymore" HallowType="1" Grades="50" NeedItemCount1="0" NeedItemCount2="1000" PropertyDatas="90800,90800,90800,544800,18160,18160" SkillTempId="41210601" EquipPetSonTypes="11702,11703"/>
	<PetHallowsTempInfo TemplateId="101051" TemplateName="Light &amp; Dark Claymore" HallowType="1" Grades="51" NeedItemCount1="400" NeedItemCount2="0" PropertyDatas="95800,95800,95800,574800,19160,19160" SkillTempId="41210601" EquipPetSonTypes="11702,11703"/>
	<PetHallowsTempInfo TemplateId="101052" TemplateName="Light &amp; Dark Claymore" HallowType="1" Grades="52" NeedItemCount1="400" NeedItemCount2="0" PropertyDatas="100800,100800,100800,604800,20160,20160" SkillTempId="41210601" EquipPetSonTypes="11702,11703"/>
	<PetHallowsTempInfo TemplateId="101053" TemplateName="Light &amp; Dark Claymore" HallowType="1" Grades="53" NeedItemCount1="400" NeedItemCount2="0" PropertyDatas="105800,105800,105800,634800,21160,21160" SkillTempId="41210601" EquipPetSonTypes="11702,11703"/>
	<PetHallowsTempInfo TemplateId="101054" TemplateName="Light &amp; Dark Claymore" HallowType="1" Grades="54" NeedItemCount1="400" NeedItemCount2="0" PropertyDatas="110800,110800,110800,664800,22160,22160" SkillTempId="41210601" EquipPetSonTypes="11702,11703"/>
	<PetHallowsTempInfo TemplateId="101055" TemplateName="Light &amp; Dark Claymore" HallowType="1" Grades="55" NeedItemCount1="400" NeedItemCount2="0" PropertyDatas="115800,115800,115800,694800,23160,23160" SkillTempId="41210601" EquipPetSonTypes="11702,11703"/>
	<PetHallowsTempInfo TemplateId="101056" TemplateName="Light &amp; Dark Claymore" HallowType="1" Grades="56" NeedItemCount1="400" NeedItemCount2="0" PropertyDatas="120800,120800,120800,724800,24160,24160" SkillTempId="41210601" EquipPetSonTypes="11702,11703"/>
	<PetHallowsTempInfo TemplateId="101057" TemplateName="Light &amp; Dark Claymore" HallowType="1" Grades="57" NeedItemCount1="400" NeedItemCount2="0" PropertyDatas="125800,125800,125800,754800,25160,25160" SkillTempId="41210601" EquipPetSonTypes="11702,11703"/>
	<PetHallowsTempInfo TemplateId="101058" TemplateName="Light &amp; Dark Claymore" HallowType="1" Grades="58" NeedItemCount1="400" NeedItemCount2="0" PropertyDatas="130800,130800,130800,784800,26160,26160" SkillTempId="41210601" EquipPetSonTypes="11702,11703"/>
	<PetHallowsTempInfo TemplateId="101059" TemplateName="Light &amp; Dark Claymore" HallowType="1" Grades="59" NeedItemCount1="400" NeedItemCount2="0" PropertyDatas="135800,135800,135800,814800,27160,27160" SkillTempId="41210601" EquipPetSonTypes="11702,11703"/>
	<PetHallowsTempInfo TemplateId="101060" TemplateName="Light &amp; Dark Claymore" HallowType="1" Grades="60" NeedItemCount1="0" NeedItemCount2="2000" PropertyDatas="135800,135800,135800,814800,27160,27160" SkillTempId="41210701" EquipPetSonTypes="11702,11703"/>
	<PetHallowsTempInfo TemplateId="101061" TemplateName="Light &amp; Dark Claymore" HallowType="1" Grades="61" NeedItemCount1="500" NeedItemCount2="0" PropertyDatas="140800,140800,140800,844800,28160,28160" SkillTempId="41210701" EquipPetSonTypes="11702,11703"/>
	<PetHallowsTempInfo TemplateId="101062" TemplateName="Light &amp; Dark Claymore" HallowType="1" Grades="62" NeedItemCount1="500" NeedItemCount2="0" PropertyDatas="145800,145800,145800,874800,29160,29160" SkillTempId="41210701" EquipPetSonTypes="11702,11703"/>
	<PetHallowsTempInfo TemplateId="101063" TemplateName="Light &amp; Dark Claymore" HallowType="1" Grades="63" NeedItemCount1="500" NeedItemCount2="0" PropertyDatas="150800,150800,150800,904800,30160,30160" SkillTempId="41210701" EquipPetSonTypes="11702,11703"/>
	<PetHallowsTempInfo TemplateId="101064" TemplateName="Light &amp; Dark Claymore" HallowType="1" Grades="64" NeedItemCount1="500" NeedItemCount2="0" PropertyDatas="155800,155800,155800,934800,31160,31160" SkillTempId="41210701" EquipPetSonTypes="11702,11703"/>
	<PetHallowsTempInfo TemplateId="101065" TemplateName="Light &amp; Dark Claymore" HallowType="1" Grades="65" NeedItemCount1="500" NeedItemCount2="0" PropertyDatas="160800,160800,160800,964800,32160,32160" SkillTempId="41210701" EquipPetSonTypes="11702,11703"/>
	<PetHallowsTempInfo TemplateId="101066" TemplateName="Light &amp; Dark Claymore" HallowType="1" Grades="66" NeedItemCount1="650" NeedItemCount2="0" PropertyDatas="165800,165800,165800,994800,33160,33160" SkillTempId="41210701" EquipPetSonTypes="11702,11703"/>
	<PetHallowsTempInfo TemplateId="101067" TemplateName="Light &amp; Dark Claymore" HallowType="1" Grades="67" NeedItemCount1="650" NeedItemCount2="0" PropertyDatas="170800,170800,170800,1024800,34160,34160" SkillTempId="41210701" EquipPetSonTypes="11702,11703"/>
	<PetHallowsTempInfo TemplateId="101068" TemplateName="Light &amp; Dark Claymore" HallowType="1" Grades="68" NeedItemCount1="650" NeedItemCount2="0" PropertyDatas="175800,175800,175800,1054800,35160,35160" SkillTempId="41210701" EquipPetSonTypes="11702,11703"/>
	<PetHallowsTempInfo TemplateId="101069" TemplateName="Light &amp; Dark Claymore" HallowType="1" Grades="69" NeedItemCount1="650" NeedItemCount2="0" PropertyDatas="180800,180800,180800,1084800,36160,36160" SkillTempId="41210701" EquipPetSonTypes="11702,11703"/>
	<PetHallowsTempInfo TemplateId="101070" TemplateName="Light &amp; Dark Claymore" HallowType="1" Grades="70" NeedItemCount1="0" NeedItemCount2="2000" PropertyDatas="180800,180800,180800,1084800,36160,36160" SkillTempId="41210801" EquipPetSonTypes="11702,11703"/>
	<PetHallowsTempInfo TemplateId="101071" TemplateName="Light &amp; Dark Claymore" HallowType="1" Grades="71" NeedItemCount1="800" NeedItemCount2="0" PropertyDatas="185800,185800,185800,1114800,37160,37160" SkillTempId="41210801" EquipPetSonTypes="11702,11703"/>
	<PetHallowsTempInfo TemplateId="101072" TemplateName="Light &amp; Dark Claymore" HallowType="1" Grades="72" NeedItemCount1="800" NeedItemCount2="0" PropertyDatas="190800,190800,190800,1144800,38160,38160" SkillTempId="41210801" EquipPetSonTypes="11702,11703"/>
	<PetHallowsTempInfo TemplateId="101073" TemplateName="Light &amp; Dark Claymore" HallowType="1" Grades="73" NeedItemCount1="800" NeedItemCount2="0" PropertyDatas="195800,195800,195800,1174800,39160,39160" SkillTempId="41210801" EquipPetSonTypes="11702,11703"/>
	<PetHallowsTempInfo TemplateId="101074" TemplateName="Light &amp; Dark Claymore" HallowType="1" Grades="74" NeedItemCount1="800" NeedItemCount2="0" PropertyDatas="200800,200800,200800,1204800,40160,40160" SkillTempId="41210801" EquipPetSonTypes="11702,11703"/>
	<PetHallowsTempInfo TemplateId="101075" TemplateName="Light &amp; Dark Claymore" HallowType="1" Grades="75" NeedItemCount1="800" NeedItemCount2="0" PropertyDatas="205800,205800,205800,1234800,41160,41160" SkillTempId="41210801" EquipPetSonTypes="11702,11703"/>
	<PetHallowsTempInfo TemplateId="101076" TemplateName="Light &amp; Dark Claymore" HallowType="1" Grades="76" NeedItemCount1="1000" NeedItemCount2="0" PropertyDatas="210800,210800,210800,1264800,42160,42160" SkillTempId="41210801" EquipPetSonTypes="11702,11703"/>
	<PetHallowsTempInfo TemplateId="101077" TemplateName="Light &amp; Dark Claymore" HallowType="1" Grades="77" NeedItemCount1="1000" NeedItemCount2="0" PropertyDatas="215800,215800,215800,1294800,43160,43160" SkillTempId="41210801" EquipPetSonTypes="11702,11703"/>
	<PetHallowsTempInfo TemplateId="101078" TemplateName="Light &amp; Dark Claymore" HallowType="1" Grades="78" NeedItemCount1="1000" NeedItemCount2="0" PropertyDatas="220800,220800,220800,1324800,44160,44160" SkillTempId="41210801" EquipPetSonTypes="11702,11703"/>
	<PetHallowsTempInfo TemplateId="101079" TemplateName="Light &amp; Dark Claymore" HallowType="1" Grades="79" NeedItemCount1="1000" NeedItemCount2="0" PropertyDatas="225800,225800,225800,1354800,45160,45160" SkillTempId="41210801" EquipPetSonTypes="11702,11703"/>
	<PetHallowsTempInfo TemplateId="101080" TemplateName="Light &amp; Dark Claymore" HallowType="1" Grades="80" NeedItemCount1="0" NeedItemCount2="4000" PropertyDatas="225800,225800,225800,1354800,45160,45160" SkillTempId="41210901" EquipPetSonTypes="11702,11703"/>
	<PetHallowsTempInfo TemplateId="101081" TemplateName="Light &amp; Dark Claymore" HallowType="1" Grades="81" NeedItemCount1="1500" NeedItemCount2="0" PropertyDatas="230800,230800,230800,1384800,46160,46160" SkillTempId="41210901" EquipPetSonTypes="11702,11703"/>
	<PetHallowsTempInfo TemplateId="101082" TemplateName="Light &amp; Dark Claymore" HallowType="1" Grades="82" NeedItemCount1="1500" NeedItemCount2="0" PropertyDatas="235800,235800,235800,1414800,47160,47160" SkillTempId="41210901" EquipPetSonTypes="11702,11703"/>
	<PetHallowsTempInfo TemplateId="101083" TemplateName="Light &amp; Dark Claymore" HallowType="1" Grades="83" NeedItemCount1="1500" NeedItemCount2="0" PropertyDatas="240800,240800,240800,1444800,48160,48160" SkillTempId="41210901" EquipPetSonTypes="11702,11703"/>
	<PetHallowsTempInfo TemplateId="101084" TemplateName="Light &amp; Dark Claymore" HallowType="1" Grades="84" NeedItemCount1="1500" NeedItemCount2="0" PropertyDatas="245800,245800,245800,1474800,49160,49160" SkillTempId="41210901" EquipPetSonTypes="11702,11703"/>
	<PetHallowsTempInfo TemplateId="101085" TemplateName="Light &amp; Dark Claymore" HallowType="1" Grades="85" NeedItemCount1="1500" NeedItemCount2="0" PropertyDatas="250800,250800,250800,1504800,50160,50160" SkillTempId="41210901" EquipPetSonTypes="11702,11703"/>
	<PetHallowsTempInfo TemplateId="101086" TemplateName="Light &amp; Dark Claymore" HallowType="1" Grades="86" NeedItemCount1="1500" NeedItemCount2="0" PropertyDatas="255800,255800,255800,1534800,51160,51160" SkillTempId="41210901" EquipPetSonTypes="11702,11703"/>
	<PetHallowsTempInfo TemplateId="101087" TemplateName="Light &amp; Dark Claymore" HallowType="1" Grades="87" NeedItemCount1="1500" NeedItemCount2="0" PropertyDatas="260800,260800,260800,1564800,52160,52160" SkillTempId="41210901" EquipPetSonTypes="11702,11703"/>
	<PetHallowsTempInfo TemplateId="101088" TemplateName="Light &amp; Dark Claymore" HallowType="1" Grades="88" NeedItemCount1="1500" NeedItemCount2="0" PropertyDatas="265800,265800,265800,1594800,53160,53160" SkillTempId="41210901" EquipPetSonTypes="11702,11703"/>
	<PetHallowsTempInfo TemplateId="101089" TemplateName="Light &amp; Dark Claymore" HallowType="1" Grades="89" NeedItemCount1="1500" NeedItemCount2="0" PropertyDatas="270800,270800,270800,1624800,54160,54160" SkillTempId="41210901" EquipPetSonTypes="11702,11703"/>
	<PetHallowsTempInfo TemplateId="101090" TemplateName="Light &amp; Dark Claymore" HallowType="1" Grades="90" NeedItemCount1="0" NeedItemCount2="5000" PropertyDatas="270800,270800,270800,1624800,54160,54160" SkillTempId="41211001" EquipPetSonTypes="11702,11703"/>
	<PetHallowsTempInfo TemplateId="101091" TemplateName="Light &amp; Dark Claymore" HallowType="1" Grades="91" NeedItemCount1="2000" NeedItemCount2="0" PropertyDatas="275800,275800,275800,1654800,55160,55160" SkillTempId="41211001" EquipPetSonTypes="11702,11703"/>
	<PetHallowsTempInfo TemplateId="101092" TemplateName="Light &amp; Dark Claymore" HallowType="1" Grades="92" NeedItemCount1="2000" NeedItemCount2="0" PropertyDatas="280800,280800,280800,1684800,56160,56160" SkillTempId="41211001" EquipPetSonTypes="11702,11703"/>
	<PetHallowsTempInfo TemplateId="101093" TemplateName="Light &amp; Dark Claymore" HallowType="1" Grades="93" NeedItemCount1="2000" NeedItemCount2="0" PropertyDatas="285800,285800,285800,1714800,57160,57160" SkillTempId="41211001" EquipPetSonTypes="11702,11703"/>
	<PetHallowsTempInfo TemplateId="101094" TemplateName="Light &amp; Dark Claymore" HallowType="1" Grades="94" NeedItemCount1="2000" NeedItemCount2="0" PropertyDatas="290800,290800,290800,1744800,58160,58160" SkillTempId="41211001" EquipPetSonTypes="11702,11703"/>
	<PetHallowsTempInfo TemplateId="101095" TemplateName="Light &amp; Dark Claymore" HallowType="1" Grades="95" NeedItemCount1="2000" NeedItemCount2="0" PropertyDatas="295800,295800,295800,1774800,59160,59160" SkillTempId="41211001" EquipPetSonTypes="11702,11703"/>
	<PetHallowsTempInfo TemplateId="101096" TemplateName="Light &amp; Dark Claymore" HallowType="1" Grades="96" NeedItemCount1="2000" NeedItemCount2="0" PropertyDatas="300800,300800,300800,1804800,60160,60160" SkillTempId="41211001" EquipPetSonTypes="11702,11703"/>
	<PetHallowsTempInfo TemplateId="101097" TemplateName="Light &amp; Dark Claymore" HallowType="1" Grades="97" NeedItemCount1="2000" NeedItemCount2="0" PropertyDatas="305800,305800,305800,1834800,61160,61160" SkillTempId="41211001" EquipPetSonTypes="11702,11703"/>
	<PetHallowsTempInfo TemplateId="101098" TemplateName="Light &amp; Dark Claymore" HallowType="1" Grades="98" NeedItemCount1="2000" NeedItemCount2="0" PropertyDatas="310800,310800,310800,1864800,62160,62160" SkillTempId="41211001" EquipPetSonTypes="11702,11703"/>
	<PetHallowsTempInfo TemplateId="101099" TemplateName="Light &amp; Dark Claymore" HallowType="1" Grades="99" NeedItemCount1="2000" NeedItemCount2="0" PropertyDatas="315800,315800,315800,1894800,63160,63160" SkillTempId="41211001" EquipPetSonTypes="11702,11703"/>
	<PetHallowsTempInfo TemplateId="102001" TemplateName="Wind &amp; Water Staff" HallowType="2" Grades="1" NeedItemCount1="20" NeedItemCount2="0" PropertyDatas="0,0,0,0,0,0" SkillTempId="41230101" EquipPetSonTypes="11802,11803"/>
	<PetHallowsTempInfo TemplateId="102002" TemplateName="Wind &amp; Water Staff" HallowType="2" Grades="2" NeedItemCount1="20" NeedItemCount2="0" PropertyDatas="500,500,500,3000,100,100" SkillTempId="41230101" EquipPetSonTypes="11802,11803"/>
	<PetHallowsTempInfo TemplateId="102003" TemplateName="Wind &amp; Water Staff" HallowType="2" Grades="3" NeedItemCount1="20" NeedItemCount2="0" PropertyDatas="1000,1000,1000,6000,200,200" SkillTempId="41230101" EquipPetSonTypes="11802,11803"/>
	<PetHallowsTempInfo TemplateId="102004" TemplateName="Wind &amp; Water Staff" HallowType="2" Grades="4" NeedItemCount1="20" NeedItemCount2="0" PropertyDatas="1500,1500,1500,9000,300,300" SkillTempId="41230101" EquipPetSonTypes="11802,11803"/>
	<PetHallowsTempInfo TemplateId="102005" TemplateName="Wind &amp; Water Staff" HallowType="2" Grades="5" NeedItemCount1="20" NeedItemCount2="0" PropertyDatas="2000,2000,2000,12000,400,400" SkillTempId="41230101" EquipPetSonTypes="11802,11803"/>
	<PetHallowsTempInfo TemplateId="102006" TemplateName="Wind &amp; Water Staff" HallowType="2" Grades="6" NeedItemCount1="40" NeedItemCount2="0" PropertyDatas="2800,2800,2800,16800,560,560" SkillTempId="41230101" EquipPetSonTypes="11802,11803"/>
	<PetHallowsTempInfo TemplateId="102007" TemplateName="Wind &amp; Water Staff" HallowType="2" Grades="7" NeedItemCount1="40" NeedItemCount2="0" PropertyDatas="3600,3600,3600,21600,720,720" SkillTempId="41230101" EquipPetSonTypes="11802,11803"/>
	<PetHallowsTempInfo TemplateId="102008" TemplateName="Wind &amp; Water Staff" HallowType="2" Grades="8" NeedItemCount1="40" NeedItemCount2="0" PropertyDatas="4400,4400,4400,26400,880,880" SkillTempId="41230101" EquipPetSonTypes="11802,11803"/>
	<PetHallowsTempInfo TemplateId="102009" TemplateName="Wind &amp; Water Staff" HallowType="2" Grades="9" NeedItemCount1="40" NeedItemCount2="0" PropertyDatas="5200,5200,5200,31200,1040,1040" SkillTempId="41230101" EquipPetSonTypes="11802,11803"/>
	<PetHallowsTempInfo TemplateId="102010" TemplateName="Wind &amp; Water Staff" HallowType="2" Grades="10" NeedItemCount1="0" NeedItemCount2="200" PropertyDatas="5200,5200,5200,31200,1040,1040" SkillTempId="41230201" EquipPetSonTypes="11802,11803"/>
	<PetHallowsTempInfo TemplateId="102011" TemplateName="Wind &amp; Water Staff" HallowType="2" Grades="11" NeedItemCount1="60" NeedItemCount2="0" PropertyDatas="6300,6300,6300,37800,1260,1260" SkillTempId="41230201" EquipPetSonTypes="11802,11803"/>
	<PetHallowsTempInfo TemplateId="102012" TemplateName="Wind &amp; Water Staff" HallowType="2" Grades="12" NeedItemCount1="60" NeedItemCount2="0" PropertyDatas="7400,7400,7400,44400,1480,1480" SkillTempId="41230201" EquipPetSonTypes="11802,11803"/>
	<PetHallowsTempInfo TemplateId="102013" TemplateName="Wind &amp; Water Staff" HallowType="2" Grades="13" NeedItemCount1="60" NeedItemCount2="0" PropertyDatas="8500,8500,8500,51000,1700,1700" SkillTempId="41230201" EquipPetSonTypes="11802,11803"/>
	<PetHallowsTempInfo TemplateId="102014" TemplateName="Wind &amp; Water Staff" HallowType="2" Grades="14" NeedItemCount1="60" NeedItemCount2="0" PropertyDatas="9600,9600,9600,57600,1920,1920" SkillTempId="41230201" EquipPetSonTypes="11802,11803"/>
	<PetHallowsTempInfo TemplateId="102015" TemplateName="Wind &amp; Water Staff" HallowType="2" Grades="15" NeedItemCount1="60" NeedItemCount2="0" PropertyDatas="10700,10700,10700,64200,2140,2140" SkillTempId="41230201" EquipPetSonTypes="11802,11803"/>
	<PetHallowsTempInfo TemplateId="102016" TemplateName="Wind &amp; Water Staff" HallowType="2" Grades="16" NeedItemCount1="80" NeedItemCount2="0" PropertyDatas="12100,12100,12100,72600,2420,2420" SkillTempId="41230201" EquipPetSonTypes="11802,11803"/>
	<PetHallowsTempInfo TemplateId="102017" TemplateName="Wind &amp; Water Staff" HallowType="2" Grades="17" NeedItemCount1="80" NeedItemCount2="0" PropertyDatas="13500,13500,13500,81000,2700,2700" SkillTempId="41230201" EquipPetSonTypes="11802,11803"/>
	<PetHallowsTempInfo TemplateId="102018" TemplateName="Wind &amp; Water Staff" HallowType="2" Grades="18" NeedItemCount1="80" NeedItemCount2="0" PropertyDatas="14900,14900,14900,89400,2980,2980" SkillTempId="41230201" EquipPetSonTypes="11802,11803"/>
	<PetHallowsTempInfo TemplateId="102019" TemplateName="Wind &amp; Water Staff" HallowType="2" Grades="19" NeedItemCount1="80" NeedItemCount2="0" PropertyDatas="16300,16300,16300,97800,3260,3260" SkillTempId="41230201" EquipPetSonTypes="11802,11803"/>
	<PetHallowsTempInfo TemplateId="102020" TemplateName="Wind &amp; Water Staff" HallowType="2" Grades="20" NeedItemCount1="0" NeedItemCount2="500" PropertyDatas="16300,16300,16300,97800,3260,3260" SkillTempId="41230301" EquipPetSonTypes="11802,11803"/>
	<PetHallowsTempInfo TemplateId="102021" TemplateName="Wind &amp; Water Staff" HallowType="2" Grades="21" NeedItemCount1="100" NeedItemCount2="0" PropertyDatas="18000,18000,18000,108000,3600,3600" SkillTempId="41230301" EquipPetSonTypes="11802,11803"/>
	<PetHallowsTempInfo TemplateId="102022" TemplateName="Wind &amp; Water Staff" HallowType="2" Grades="22" NeedItemCount1="100" NeedItemCount2="0" PropertyDatas="19700,19700,19700,118200,3940,3940" SkillTempId="41230301" EquipPetSonTypes="11802,11803"/>
	<PetHallowsTempInfo TemplateId="102023" TemplateName="Wind &amp; Water Staff" HallowType="2" Grades="23" NeedItemCount1="100" NeedItemCount2="0" PropertyDatas="21400,21400,21400,128400,4280,4280" SkillTempId="41230301" EquipPetSonTypes="11802,11803"/>
	<PetHallowsTempInfo TemplateId="102024" TemplateName="Wind &amp; Water Staff" HallowType="2" Grades="24" NeedItemCount1="100" NeedItemCount2="0" PropertyDatas="23100,23100,23100,138600,4620,4620" SkillTempId="41230301" EquipPetSonTypes="11802,11803"/>
	<PetHallowsTempInfo TemplateId="102025" TemplateName="Wind &amp; Water Staff" HallowType="2" Grades="25" NeedItemCount1="100" NeedItemCount2="0" PropertyDatas="24800,24800,24800,148800,4960,4960" SkillTempId="41230301" EquipPetSonTypes="11802,11803"/>
	<PetHallowsTempInfo TemplateId="102026" TemplateName="Wind &amp; Water Staff" HallowType="2" Grades="26" NeedItemCount1="150" NeedItemCount2="0" PropertyDatas="26800,26800,26800,160800,5360,5360" SkillTempId="41230301" EquipPetSonTypes="11802,11803"/>
	<PetHallowsTempInfo TemplateId="102027" TemplateName="Wind &amp; Water Staff" HallowType="2" Grades="27" NeedItemCount1="150" NeedItemCount2="0" PropertyDatas="28800,28800,28800,172800,5760,5760" SkillTempId="41230301" EquipPetSonTypes="11802,11803"/>
	<PetHallowsTempInfo TemplateId="102028" TemplateName="Wind &amp; Water Staff" HallowType="2" Grades="28" NeedItemCount1="150" NeedItemCount2="0" PropertyDatas="30800,30800,30800,184800,6160,6160" SkillTempId="41230301" EquipPetSonTypes="11802,11803"/>
	<PetHallowsTempInfo TemplateId="102029" TemplateName="Wind &amp; Water Staff" HallowType="2" Grades="29" NeedItemCount1="150" NeedItemCount2="0" PropertyDatas="32800,32800,32800,196800,6560,6560" SkillTempId="41230301" EquipPetSonTypes="11802,11803"/>
	<PetHallowsTempInfo TemplateId="102030" TemplateName="Wind &amp; Water Staff" HallowType="2" Grades="30" NeedItemCount1="0" NeedItemCount2="1000" PropertyDatas="32800,32800,32800,196800,6560,6560" SkillTempId="41230401" EquipPetSonTypes="11802,11803"/>
	<PetHallowsTempInfo TemplateId="102031" TemplateName="Wind &amp; Water Staff" HallowType="2" Grades="31" NeedItemCount1="200" NeedItemCount2="0" PropertyDatas="35300,35300,35300,211800,7060,7060" SkillTempId="41230401" EquipPetSonTypes="11802,11803"/>
	<PetHallowsTempInfo TemplateId="102032" TemplateName="Wind &amp; Water Staff" HallowType="2" Grades="32" NeedItemCount1="200" NeedItemCount2="0" PropertyDatas="37800,37800,37800,226800,7560,7560" SkillTempId="41230401" EquipPetSonTypes="11802,11803"/>
	<PetHallowsTempInfo TemplateId="102033" TemplateName="Wind &amp; Water Staff" HallowType="2" Grades="33" NeedItemCount1="200" NeedItemCount2="0" PropertyDatas="40300,40300,40300,241800,8060,8060" SkillTempId="41230401" EquipPetSonTypes="11802,11803"/>
	<PetHallowsTempInfo TemplateId="102034" TemplateName="Wind &amp; Water Staff" HallowType="2" Grades="34" NeedItemCount1="200" NeedItemCount2="0" PropertyDatas="42800,42800,42800,256800,8560,8560" SkillTempId="41230401" EquipPetSonTypes="11802,11803"/>
	<PetHallowsTempInfo TemplateId="102035" TemplateName="Wind &amp; Water Staff" HallowType="2" Grades="35" NeedItemCount1="200" NeedItemCount2="0" PropertyDatas="45300,45300,45300,271800,9060,9060" SkillTempId="41230401" EquipPetSonTypes="11802,11803"/>
	<PetHallowsTempInfo TemplateId="102036" TemplateName="Wind &amp; Water Staff" HallowType="2" Grades="36" NeedItemCount1="250" NeedItemCount2="0" PropertyDatas="48300,48300,48300,289800,9660,9660" SkillTempId="41230401" EquipPetSonTypes="11802,11803"/>
	<PetHallowsTempInfo TemplateId="102037" TemplateName="Wind &amp; Water Staff" HallowType="2" Grades="37" NeedItemCount1="250" NeedItemCount2="0" PropertyDatas="51300,51300,51300,307800,10260,10260" SkillTempId="41230401" EquipPetSonTypes="11802,11803"/>
	<PetHallowsTempInfo TemplateId="102038" TemplateName="Wind &amp; Water Staff" HallowType="2" Grades="38" NeedItemCount1="250" NeedItemCount2="0" PropertyDatas="54300,54300,54300,325800,10860,10860" SkillTempId="41230401" EquipPetSonTypes="11802,11803"/>
	<PetHallowsTempInfo TemplateId="102039" TemplateName="Wind &amp; Water Staff" HallowType="2" Grades="39" NeedItemCount1="250" NeedItemCount2="0" PropertyDatas="57300,57300,57300,343800,11460,11460" SkillTempId="41230401" EquipPetSonTypes="11802,11803"/>
	<PetHallowsTempInfo TemplateId="102040" TemplateName="Wind &amp; Water Staff" HallowType="2" Grades="40" NeedItemCount1="0" NeedItemCount2="1000" PropertyDatas="57300,57300,57300,343800,11460,11460" SkillTempId="41230501" EquipPetSonTypes="11802,11803"/>
	<PetHallowsTempInfo TemplateId="102041" TemplateName="Wind &amp; Water Staff" HallowType="2" Grades="41" NeedItemCount1="300" NeedItemCount2="0" PropertyDatas="60800,60800,60800,364800,12160,12160" SkillTempId="41230501" EquipPetSonTypes="11802,11803"/>
	<PetHallowsTempInfo TemplateId="102042" TemplateName="Wind &amp; Water Staff" HallowType="2" Grades="42" NeedItemCount1="300" NeedItemCount2="0" PropertyDatas="64300,64300,64300,385800,12860,12860" SkillTempId="41230501" EquipPetSonTypes="11802,11803"/>
	<PetHallowsTempInfo TemplateId="102043" TemplateName="Wind &amp; Water Staff" HallowType="2" Grades="43" NeedItemCount1="300" NeedItemCount2="0" PropertyDatas="67800,67800,67800,406800,13560,13560" SkillTempId="41230501" EquipPetSonTypes="11802,11803"/>
	<PetHallowsTempInfo TemplateId="102044" TemplateName="Wind &amp; Water Staff" HallowType="2" Grades="44" NeedItemCount1="300" NeedItemCount2="0" PropertyDatas="71300,71300,71300,427800,14260,14260" SkillTempId="41230501" EquipPetSonTypes="11802,11803"/>
	<PetHallowsTempInfo TemplateId="102045" TemplateName="Wind &amp; Water Staff" HallowType="2" Grades="45" NeedItemCount1="300" NeedItemCount2="0" PropertyDatas="74800,74800,74800,448800,14960,14960" SkillTempId="41230501" EquipPetSonTypes="11802,11803"/>
	<PetHallowsTempInfo TemplateId="102046" TemplateName="Wind &amp; Water Staff" HallowType="2" Grades="46" NeedItemCount1="350" NeedItemCount2="0" PropertyDatas="78800,78800,78800,472800,15760,15760" SkillTempId="41230501" EquipPetSonTypes="11802,11803"/>
	<PetHallowsTempInfo TemplateId="102047" TemplateName="Wind &amp; Water Staff" HallowType="2" Grades="47" NeedItemCount1="350" NeedItemCount2="0" PropertyDatas="82800,82800,82800,496800,16560,16560" SkillTempId="41230501" EquipPetSonTypes="11802,11803"/>
	<PetHallowsTempInfo TemplateId="102048" TemplateName="Wind &amp; Water Staff" HallowType="2" Grades="48" NeedItemCount1="350" NeedItemCount2="0" PropertyDatas="86800,86800,86800,520800,17360,17360" SkillTempId="41230501" EquipPetSonTypes="11802,11803"/>
	<PetHallowsTempInfo TemplateId="102049" TemplateName="Wind &amp; Water Staff" HallowType="2" Grades="49" NeedItemCount1="350" NeedItemCount2="0" PropertyDatas="90800,90800,90800,544800,18160,18160" SkillTempId="41230501" EquipPetSonTypes="11802,11803"/>
	<PetHallowsTempInfo TemplateId="102050" TemplateName="Wind &amp; Water Staff" HallowType="2" Grades="50" NeedItemCount1="0" NeedItemCount2="1000" PropertyDatas="90800,90800,90800,544800,18160,18160" SkillTempId="41230601" EquipPetSonTypes="11802,11803"/>
	<PetHallowsTempInfo TemplateId="102051" TemplateName="Wind &amp; Water Staff" HallowType="2" Grades="51" NeedItemCount1="400" NeedItemCount2="0" PropertyDatas="95800,95800,95800,574800,19160,19160" SkillTempId="41230601" EquipPetSonTypes="11802,11803"/>
	<PetHallowsTempInfo TemplateId="102052" TemplateName="Wind &amp; Water Staff" HallowType="2" Grades="52" NeedItemCount1="400" NeedItemCount2="0" PropertyDatas="100800,100800,100800,604800,20160,20160" SkillTempId="41230601" EquipPetSonTypes="11802,11803"/>
	<PetHallowsTempInfo TemplateId="102053" TemplateName="Wind &amp; Water Staff" HallowType="2" Grades="53" NeedItemCount1="400" NeedItemCount2="0" PropertyDatas="105800,105800,105800,634800,21160,21160" SkillTempId="41230601" EquipPetSonTypes="11802,11803"/>
	<PetHallowsTempInfo TemplateId="102054" TemplateName="Wind &amp; Water Staff" HallowType="2" Grades="54" NeedItemCount1="400" NeedItemCount2="0" PropertyDatas="110800,110800,110800,664800,22160,22160" SkillTempId="41230601" EquipPetSonTypes="11802,11803"/>
	<PetHallowsTempInfo TemplateId="102055" TemplateName="Wind &amp; Water Staff" HallowType="2" Grades="55" NeedItemCount1="400" NeedItemCount2="0" PropertyDatas="115800,115800,115800,694800,23160,23160" SkillTempId="41230601" EquipPetSonTypes="11802,11803"/>
	<PetHallowsTempInfo TemplateId="102056" TemplateName="Wind &amp; Water Staff" HallowType="2" Grades="56" NeedItemCount1="400" NeedItemCount2="0" PropertyDatas="120800,120800,120800,724800,24160,24160" SkillTempId="41230601" EquipPetSonTypes="11802,11803"/>
	<PetHallowsTempInfo TemplateId="102057" TemplateName="Wind &amp; Water Staff" HallowType="2" Grades="57" NeedItemCount1="400" NeedItemCount2="0" PropertyDatas="125800,125800,125800,754800,25160,25160" SkillTempId="41230601" EquipPetSonTypes="11802,11803"/>
	<PetHallowsTempInfo TemplateId="102058" TemplateName="Wind &amp; Water Staff" HallowType="2" Grades="58" NeedItemCount1="400" NeedItemCount2="0" PropertyDatas="130800,130800,130800,784800,26160,26160" SkillTempId="41230601" EquipPetSonTypes="11802,11803"/>
	<PetHallowsTempInfo TemplateId="102059" TemplateName="Wind &amp; Water Staff" HallowType="2" Grades="59" NeedItemCount1="400" NeedItemCount2="0" PropertyDatas="135800,135800,135800,814800,27160,27160" SkillTempId="41230601" EquipPetSonTypes="11802,11803"/>
	<PetHallowsTempInfo TemplateId="102060" TemplateName="Wind &amp; Water Staff" HallowType="2" Grades="60" NeedItemCount1="0" NeedItemCount2="2000" PropertyDatas="135800,135800,135800,814800,27160,27160" SkillTempId="41230701" EquipPetSonTypes="11802,11803"/>
	<PetHallowsTempInfo TemplateId="102061" TemplateName="Wind &amp; Water Staff" HallowType="2" Grades="61" NeedItemCount1="500" NeedItemCount2="0" PropertyDatas="140800,140800,140800,844800,28160,28160" SkillTempId="41230701" EquipPetSonTypes="11802,11803"/>
	<PetHallowsTempInfo TemplateId="102062" TemplateName="Wind &amp; Water Staff" HallowType="2" Grades="62" NeedItemCount1="500" NeedItemCount2="0" PropertyDatas="145800,145800,145800,874800,29160,29160" SkillTempId="41230701" EquipPetSonTypes="11802,11803"/>
	<PetHallowsTempInfo TemplateId="102063" TemplateName="Wind &amp; Water Staff" HallowType="2" Grades="63" NeedItemCount1="500" NeedItemCount2="0" PropertyDatas="150800,150800,150800,904800,30160,30160" SkillTempId="41230701" EquipPetSonTypes="11802,11803"/>
	<PetHallowsTempInfo TemplateId="102064" TemplateName="Wind &amp; Water Staff" HallowType="2" Grades="64" NeedItemCount1="500" NeedItemCount2="0" PropertyDatas="155800,155800,155800,934800,31160,31160" SkillTempId="41230701" EquipPetSonTypes="11802,11803"/>
	<PetHallowsTempInfo TemplateId="102065" TemplateName="Wind &amp; Water Staff" HallowType="2" Grades="65" NeedItemCount1="500" NeedItemCount2="0" PropertyDatas="160800,160800,160800,964800,32160,32160" SkillTempId="41230701" EquipPetSonTypes="11802,11803"/>
	<PetHallowsTempInfo TemplateId="102066" TemplateName="Wind &amp; Water Staff" HallowType="2" Grades="66" NeedItemCount1="650" NeedItemCount2="0" PropertyDatas="165800,165800,165800,994800,33160,33160" SkillTempId="41230701" EquipPetSonTypes="11802,11803"/>
	<PetHallowsTempInfo TemplateId="102067" TemplateName="Wind &amp; Water Staff" HallowType="2" Grades="67" NeedItemCount1="650" NeedItemCount2="0" PropertyDatas="170800,170800,170800,1024800,34160,34160" SkillTempId="41230701" EquipPetSonTypes="11802,11803"/>
	<PetHallowsTempInfo TemplateId="102068" TemplateName="Wind &amp; Water Staff" HallowType="2" Grades="68" NeedItemCount1="650" NeedItemCount2="0" PropertyDatas="175800,175800,175800,1054800,35160,35160" SkillTempId="41230701" EquipPetSonTypes="11802,11803"/>
	<PetHallowsTempInfo TemplateId="102069" TemplateName="Wind &amp; Water Staff" HallowType="2" Grades="69" NeedItemCount1="650" NeedItemCount2="0" PropertyDatas="180800,180800,180800,1084800,36160,36160" SkillTempId="41230701" EquipPetSonTypes="11802,11803"/>
	<PetHallowsTempInfo TemplateId="102070" TemplateName="Wind &amp; Water Staff" HallowType="2" Grades="70" NeedItemCount1="0" NeedItemCount2="2000" PropertyDatas="180800,180800,180800,1084800,36160,36160" SkillTempId="41230801" EquipPetSonTypes="11802,11803"/>
	<PetHallowsTempInfo TemplateId="102071" TemplateName="Wind &amp; Water Staff" HallowType="2" Grades="71" NeedItemCount1="800" NeedItemCount2="0" PropertyDatas="185800,185800,185800,1114800,37160,37160" SkillTempId="41230801" EquipPetSonTypes="11802,11803"/>
	<PetHallowsTempInfo TemplateId="102072" TemplateName="Wind &amp; Water Staff" HallowType="2" Grades="72" NeedItemCount1="800" NeedItemCount2="0" PropertyDatas="190800,190800,190800,1144800,38160,38160" SkillTempId="41230801" EquipPetSonTypes="11802,11803"/>
	<PetHallowsTempInfo TemplateId="102073" TemplateName="Wind &amp; Water Staff" HallowType="2" Grades="73" NeedItemCount1="800" NeedItemCount2="0" PropertyDatas="195800,195800,195800,1174800,39160,39160" SkillTempId="41230801" EquipPetSonTypes="11802,11803"/>
	<PetHallowsTempInfo TemplateId="102074" TemplateName="Wind &amp; Water Staff" HallowType="2" Grades="74" NeedItemCount1="800" NeedItemCount2="0" PropertyDatas="200800,200800,200800,1204800,40160,40160" SkillTempId="41230801" EquipPetSonTypes="11802,11803"/>
	<PetHallowsTempInfo TemplateId="102075" TemplateName="Wind &amp; Water Staff" HallowType="2" Grades="75" NeedItemCount1="800" NeedItemCount2="0" PropertyDatas="205800,205800,205800,1234800,41160,41160" SkillTempId="41230801" EquipPetSonTypes="11802,11803"/>
	<PetHallowsTempInfo TemplateId="102076" TemplateName="Wind &amp; Water Staff" HallowType="2" Grades="76" NeedItemCount1="1000" NeedItemCount2="0" PropertyDatas="210800,210800,210800,1264800,42160,42160" SkillTempId="41230801" EquipPetSonTypes="11802,11803"/>
	<PetHallowsTempInfo TemplateId="102077" TemplateName="Wind &amp; Water Staff" HallowType="2" Grades="77" NeedItemCount1="1000" NeedItemCount2="0" PropertyDatas="215800,215800,215800,1294800,43160,43160" SkillTempId="41230801" EquipPetSonTypes="11802,11803"/>
	<PetHallowsTempInfo TemplateId="102078" TemplateName="Wind &amp; Water Staff" HallowType="2" Grades="78" NeedItemCount1="1000" NeedItemCount2="0" PropertyDatas="220800,220800,220800,1324800,44160,44160" SkillTempId="41230801" EquipPetSonTypes="11802,11803"/>
	<PetHallowsTempInfo TemplateId="102079" TemplateName="Wind &amp; Water Staff" HallowType="2" Grades="79" NeedItemCount1="1000" NeedItemCount2="0" PropertyDatas="225800,225800,225800,1354800,45160,45160" SkillTempId="41230801" EquipPetSonTypes="11802,11803"/>
	<PetHallowsTempInfo TemplateId="102080" TemplateName="Wind &amp; Water Staff" HallowType="2" Grades="80" NeedItemCount1="0" NeedItemCount2="4000" PropertyDatas="225800,225800,225800,1354800,45160,45160" SkillTempId="41230901" EquipPetSonTypes="11802,11803"/>
	<PetHallowsTempInfo TemplateId="102081" TemplateName="Wind &amp; Water Staff" HallowType="2" Grades="81" NeedItemCount1="1500" NeedItemCount2="0" PropertyDatas="230800,230800,230800,1384800,46160,46160" SkillTempId="41230901" EquipPetSonTypes="11802,11803"/>
	<PetHallowsTempInfo TemplateId="102082" TemplateName="Wind &amp; Water Staff" HallowType="2" Grades="82" NeedItemCount1="1500" NeedItemCount2="0" PropertyDatas="235800,235800,235800,1414800,47160,47160" SkillTempId="41230901" EquipPetSonTypes="11802,11803"/>
	<PetHallowsTempInfo TemplateId="102083" TemplateName="Wind &amp; Water Staff" HallowType="2" Grades="83" NeedItemCount1="1500" NeedItemCount2="0" PropertyDatas="240800,240800,240800,1444800,48160,48160" SkillTempId="41230901" EquipPetSonTypes="11802,11803"/>
	<PetHallowsTempInfo TemplateId="102084" TemplateName="Wind &amp; Water Staff" HallowType="2" Grades="84" NeedItemCount1="1500" NeedItemCount2="0" PropertyDatas="245800,245800,245800,1474800,49160,49160" SkillTempId="41230901" EquipPetSonTypes="11802,11803"/>
	<PetHallowsTempInfo TemplateId="102085" TemplateName="Wind &amp; Water Staff" HallowType="2" Grades="85" NeedItemCount1="1500" NeedItemCount2="0" PropertyDatas="250800,250800,250800,1504800,50160,50160" SkillTempId="41230901" EquipPetSonTypes="11802,11803"/>
	<PetHallowsTempInfo TemplateId="102086" TemplateName="Wind &amp; Water Staff" HallowType="2" Grades="86" NeedItemCount1="1500" NeedItemCount2="0" PropertyDatas="255800,255800,255800,1534800,51160,51160" SkillTempId="41230901" EquipPetSonTypes="11802,11803"/>
	<PetHallowsTempInfo TemplateId="102087" TemplateName="Wind &amp; Water Staff" HallowType="2" Grades="87" NeedItemCount1="1500" NeedItemCount2="0" PropertyDatas="260800,260800,260800,1564800,52160,52160" SkillTempId="41230901" EquipPetSonTypes="11802,11803"/>
	<PetHallowsTempInfo TemplateId="102088" TemplateName="Wind &amp; Water Staff" HallowType="2" Grades="88" NeedItemCount1="1500" NeedItemCount2="0" PropertyDatas="265800,265800,265800,1594800,53160,53160" SkillTempId="41230901" EquipPetSonTypes="11802,11803"/>
	<PetHallowsTempInfo TemplateId="102089" TemplateName="Wind &amp; Water Staff" HallowType="2" Grades="89" NeedItemCount1="1500" NeedItemCount2="0" PropertyDatas="270800,270800,270800,1624800,54160,54160" SkillTempId="41230901" EquipPetSonTypes="11802,11803"/>
	<PetHallowsTempInfo TemplateId="102090" TemplateName="Wind &amp; Water Staff" HallowType="2" Grades="90" NeedItemCount1="0" NeedItemCount2="5000" PropertyDatas="270800,270800,270800,1624800,54160,54160" SkillTempId="41231001" EquipPetSonTypes="11802,11803"/>
	<PetHallowsTempInfo TemplateId="102091" TemplateName="Wind &amp; Water Staff" HallowType="2" Grades="91" NeedItemCount1="2000" NeedItemCount2="0" PropertyDatas="275800,275800,275800,1654800,55160,55160" SkillTempId="41231001" EquipPetSonTypes="11802,11803"/>
	<PetHallowsTempInfo TemplateId="102092" TemplateName="Wind &amp; Water Staff" HallowType="2" Grades="92" NeedItemCount1="2000" NeedItemCount2="0" PropertyDatas="280800,280800,280800,1684800,56160,56160" SkillTempId="41231001" EquipPetSonTypes="11802,11803"/>
	<PetHallowsTempInfo TemplateId="102093" TemplateName="Wind &amp; Water Staff" HallowType="2" Grades="93" NeedItemCount1="2000" NeedItemCount2="0" PropertyDatas="285800,285800,285800,1714800,57160,57160" SkillTempId="41231001" EquipPetSonTypes="11802,11803"/>
	<PetHallowsTempInfo TemplateId="102094" TemplateName="Wind &amp; Water Staff" HallowType="2" Grades="94" NeedItemCount1="2000" NeedItemCount2="0" PropertyDatas="290800,290800,290800,1744800,58160,58160" SkillTempId="41231001" EquipPetSonTypes="11802,11803"/>
	<PetHallowsTempInfo TemplateId="102095" TemplateName="Wind &amp; Water Staff" HallowType="2" Grades="95" NeedItemCount1="2000" NeedItemCount2="0" PropertyDatas="295800,295800,295800,1774800,59160,59160" SkillTempId="41231001" EquipPetSonTypes="11802,11803"/>
	<PetHallowsTempInfo TemplateId="102096" TemplateName="Wind &amp; Water Staff" HallowType="2" Grades="96" NeedItemCount1="2000" NeedItemCount2="0" PropertyDatas="300800,300800,300800,1804800,60160,60160" SkillTempId="41231001" EquipPetSonTypes="11802,11803"/>
	<PetHallowsTempInfo TemplateId="102097" TemplateName="Wind &amp; Water Staff" HallowType="2" Grades="97" NeedItemCount1="2000" NeedItemCount2="0" PropertyDatas="305800,305800,305800,1834800,61160,61160" SkillTempId="41231001" EquipPetSonTypes="11802,11803"/>
	<PetHallowsTempInfo TemplateId="102098" TemplateName="Wind &amp; Water Staff" HallowType="2" Grades="98" NeedItemCount1="2000" NeedItemCount2="0" PropertyDatas="310800,310800,310800,1864800,62160,62160" SkillTempId="41231001" EquipPetSonTypes="11802,11803"/>
	<PetHallowsTempInfo TemplateId="102099" TemplateName="Wind &amp; Water Staff" HallowType="2" Grades="99" NeedItemCount1="2000" NeedItemCount2="0" PropertyDatas="315800,315800,315800,1894800,63160,63160" SkillTempId="41231001" EquipPetSonTypes="11802,11803"/>
	<PetHallowsTempInfo TemplateId="103001" TemplateName="Fire &amp; Electro Warhammer" HallowType="3" Grades="1" NeedItemCount1="20" NeedItemCount2="0" PropertyDatas="0,0,0,0,0,0" SkillTempId="41220101" EquipPetSonTypes="11902,11903"/>
	<PetHallowsTempInfo TemplateId="103002" TemplateName="Fire &amp; Electro Warhammer" HallowType="3" Grades="2" NeedItemCount1="20" NeedItemCount2="0" PropertyDatas="500,500,500,3000,100,100" SkillTempId="41220101" EquipPetSonTypes="11902,11903"/>
	<PetHallowsTempInfo TemplateId="103003" TemplateName="Fire &amp; Electro Warhammer" HallowType="3" Grades="3" NeedItemCount1="20" NeedItemCount2="0" PropertyDatas="1000,1000,1000,6000,200,200" SkillTempId="41220101" EquipPetSonTypes="11902,11903"/>
	<PetHallowsTempInfo TemplateId="103004" TemplateName="Fire &amp; Electro Warhammer" HallowType="3" Grades="4" NeedItemCount1="20" NeedItemCount2="0" PropertyDatas="1500,1500,1500,9000,300,300" SkillTempId="41220101" EquipPetSonTypes="11902,11903"/>
	<PetHallowsTempInfo TemplateId="103005" TemplateName="Fire &amp; Electro Warhammer" HallowType="3" Grades="5" NeedItemCount1="20" NeedItemCount2="0" PropertyDatas="2000,2000,2000,12000,400,400" SkillTempId="41220101" EquipPetSonTypes="11902,11903"/>
	<PetHallowsTempInfo TemplateId="103006" TemplateName="Fire &amp; Electro Warhammer" HallowType="3" Grades="6" NeedItemCount1="40" NeedItemCount2="0" PropertyDatas="2800,2800,2800,16800,560,560" SkillTempId="41220101" EquipPetSonTypes="11902,11903"/>
	<PetHallowsTempInfo TemplateId="103007" TemplateName="Fire &amp; Electro Warhammer" HallowType="3" Grades="7" NeedItemCount1="40" NeedItemCount2="0" PropertyDatas="3600,3600,3600,21600,720,720" SkillTempId="41220101" EquipPetSonTypes="11902,11903"/>
	<PetHallowsTempInfo TemplateId="103008" TemplateName="Fire &amp; Electro Warhammer" HallowType="3" Grades="8" NeedItemCount1="40" NeedItemCount2="0" PropertyDatas="4400,4400,4400,26400,880,880" SkillTempId="41220101" EquipPetSonTypes="11902,11903"/>
	<PetHallowsTempInfo TemplateId="103009" TemplateName="Fire &amp; Electro Warhammer" HallowType="3" Grades="9" NeedItemCount1="40" NeedItemCount2="0" PropertyDatas="5200,5200,5200,31200,1040,1040" SkillTempId="41220101" EquipPetSonTypes="11902,11903"/>
	<PetHallowsTempInfo TemplateId="103010" TemplateName="Fire &amp; Electro Warhammer" HallowType="3" Grades="10" NeedItemCount1="0" NeedItemCount2="200" PropertyDatas="5200,5200,5200,31200,1040,1040" SkillTempId="41220201" EquipPetSonTypes="11902,11903"/>
	<PetHallowsTempInfo TemplateId="103011" TemplateName="Fire &amp; Electro Warhammer" HallowType="3" Grades="11" NeedItemCount1="60" NeedItemCount2="0" PropertyDatas="6300,6300,6300,37800,1260,1260" SkillTempId="41220201" EquipPetSonTypes="11902,11903"/>
	<PetHallowsTempInfo TemplateId="103012" TemplateName="Fire &amp; Electro Warhammer" HallowType="3" Grades="12" NeedItemCount1="60" NeedItemCount2="0" PropertyDatas="7400,7400,7400,44400,1480,1480" SkillTempId="41220201" EquipPetSonTypes="11902,11903"/>
	<PetHallowsTempInfo TemplateId="103013" TemplateName="Fire &amp; Electro Warhammer" HallowType="3" Grades="13" NeedItemCount1="60" NeedItemCount2="0" PropertyDatas="8500,8500,8500,51000,1700,1700" SkillTempId="41220201" EquipPetSonTypes="11902,11903"/>
	<PetHallowsTempInfo TemplateId="103014" TemplateName="Fire &amp; Electro Warhammer" HallowType="3" Grades="14" NeedItemCount1="60" NeedItemCount2="0" PropertyDatas="9600,9600,9600,57600,1920,1920" SkillTempId="41220201" EquipPetSonTypes="11902,11903"/>
	<PetHallowsTempInfo TemplateId="103015" TemplateName="Fire &amp; Electro Warhammer" HallowType="3" Grades="15" NeedItemCount1="60" NeedItemCount2="0" PropertyDatas="10700,10700,10700,64200,2140,2140" SkillTempId="41220201" EquipPetSonTypes="11902,11903"/>
	<PetHallowsTempInfo TemplateId="103016" TemplateName="Fire &amp; Electro Warhammer" HallowType="3" Grades="16" NeedItemCount1="80" NeedItemCount2="0" PropertyDatas="12100,12100,12100,72600,2420,2420" SkillTempId="41220201" EquipPetSonTypes="11902,11903"/>
	<PetHallowsTempInfo TemplateId="103017" TemplateName="Fire &amp; Electro Warhammer" HallowType="3" Grades="17" NeedItemCount1="80" NeedItemCount2="0" PropertyDatas="13500,13500,13500,81000,2700,2700" SkillTempId="41220201" EquipPetSonTypes="11902,11903"/>
	<PetHallowsTempInfo TemplateId="103018" TemplateName="Fire &amp; Electro Warhammer" HallowType="3" Grades="18" NeedItemCount1="80" NeedItemCount2="0" PropertyDatas="14900,14900,14900,89400,2980,2980" SkillTempId="41220201" EquipPetSonTypes="11902,11903"/>
	<PetHallowsTempInfo TemplateId="103019" TemplateName="Fire &amp; Electro Warhammer" HallowType="3" Grades="19" NeedItemCount1="80" NeedItemCount2="0" PropertyDatas="16300,16300,16300,97800,3260,3260" SkillTempId="41220201" EquipPetSonTypes="11902,11903"/>
	<PetHallowsTempInfo TemplateId="103020" TemplateName="Fire &amp; Electro Warhammer" HallowType="3" Grades="20" NeedItemCount1="0" NeedItemCount2="500" PropertyDatas="16300,16300,16300,97800,3260,3260" SkillTempId="41220301" EquipPetSonTypes="11902,11903"/>
	<PetHallowsTempInfo TemplateId="103021" TemplateName="Fire &amp; Electro Warhammer" HallowType="3" Grades="21" NeedItemCount1="100" NeedItemCount2="0" PropertyDatas="18000,18000,18000,108000,3600,3600" SkillTempId="41220301" EquipPetSonTypes="11902,11903"/>
	<PetHallowsTempInfo TemplateId="103022" TemplateName="Fire &amp; Electro Warhammer" HallowType="3" Grades="22" NeedItemCount1="100" NeedItemCount2="0" PropertyDatas="19700,19700,19700,118200,3940,3940" SkillTempId="41220301" EquipPetSonTypes="11902,11903"/>
	<PetHallowsTempInfo TemplateId="103023" TemplateName="Fire &amp; Electro Warhammer" HallowType="3" Grades="23" NeedItemCount1="100" NeedItemCount2="0" PropertyDatas="21400,21400,21400,128400,4280,4280" SkillTempId="41220301" EquipPetSonTypes="11902,11903"/>
	<PetHallowsTempInfo TemplateId="103024" TemplateName="Fire &amp; Electro Warhammer" HallowType="3" Grades="24" NeedItemCount1="100" NeedItemCount2="0" PropertyDatas="23100,23100,23100,138600,4620,4620" SkillTempId="41220301" EquipPetSonTypes="11902,11903"/>
	<PetHallowsTempInfo TemplateId="103025" TemplateName="Fire &amp; Electro Warhammer" HallowType="3" Grades="25" NeedItemCount1="100" NeedItemCount2="0" PropertyDatas="24800,24800,24800,148800,4960,4960" SkillTempId="41220301" EquipPetSonTypes="11902,11903"/>
	<PetHallowsTempInfo TemplateId="103026" TemplateName="Fire &amp; Electro Warhammer" HallowType="3" Grades="26" NeedItemCount1="150" NeedItemCount2="0" PropertyDatas="26800,26800,26800,160800,5360,5360" SkillTempId="41220301" EquipPetSonTypes="11902,11903"/>
	<PetHallowsTempInfo TemplateId="103027" TemplateName="Fire &amp; Electro Warhammer" HallowType="3" Grades="27" NeedItemCount1="150" NeedItemCount2="0" PropertyDatas="28800,28800,28800,172800,5760,5760" SkillTempId="41220301" EquipPetSonTypes="11902,11903"/>
	<PetHallowsTempInfo TemplateId="103028" TemplateName="Fire &amp; Electro Warhammer" HallowType="3" Grades="28" NeedItemCount1="150" NeedItemCount2="0" PropertyDatas="30800,30800,30800,184800,6160,6160" SkillTempId="41220301" EquipPetSonTypes="11902,11903"/>
	<PetHallowsTempInfo TemplateId="103029" TemplateName="Fire &amp; Electro Warhammer" HallowType="3" Grades="29" NeedItemCount1="150" NeedItemCount2="0" PropertyDatas="32800,32800,32800,196800,6560,6560" SkillTempId="41220301" EquipPetSonTypes="11902,11903"/>
	<PetHallowsTempInfo TemplateId="103030" TemplateName="Fire &amp; Electro Warhammer" HallowType="3" Grades="30" NeedItemCount1="0" NeedItemCount2="1000" PropertyDatas="32800,32800,32800,196800,6560,6560" SkillTempId="41220401" EquipPetSonTypes="11902,11903"/>
	<PetHallowsTempInfo TemplateId="103031" TemplateName="Fire &amp; Electro Warhammer" HallowType="3" Grades="31" NeedItemCount1="200" NeedItemCount2="0" PropertyDatas="35300,35300,35300,211800,7060,7060" SkillTempId="41220401" EquipPetSonTypes="11902,11903"/>
	<PetHallowsTempInfo TemplateId="103032" TemplateName="Fire &amp; Electro Warhammer" HallowType="3" Grades="32" NeedItemCount1="200" NeedItemCount2="0" PropertyDatas="37800,37800,37800,226800,7560,7560" SkillTempId="41220401" EquipPetSonTypes="11902,11903"/>
	<PetHallowsTempInfo TemplateId="103033" TemplateName="Fire &amp; Electro Warhammer" HallowType="3" Grades="33" NeedItemCount1="200" NeedItemCount2="0" PropertyDatas="40300,40300,40300,241800,8060,8060" SkillTempId="41220401" EquipPetSonTypes="11902,11903"/>
	<PetHallowsTempInfo TemplateId="103034" TemplateName="Fire &amp; Electro Warhammer" HallowType="3" Grades="34" NeedItemCount1="200" NeedItemCount2="0" PropertyDatas="42800,42800,42800,256800,8560,8560" SkillTempId="41220401" EquipPetSonTypes="11902,11903"/>
	<PetHallowsTempInfo TemplateId="103035" TemplateName="Fire &amp; Electro Warhammer" HallowType="3" Grades="35" NeedItemCount1="200" NeedItemCount2="0" PropertyDatas="45300,45300,45300,271800,9060,9060" SkillTempId="41220401" EquipPetSonTypes="11902,11903"/>
	<PetHallowsTempInfo TemplateId="103036" TemplateName="Fire &amp; Electro Warhammer" HallowType="3" Grades="36" NeedItemCount1="250" NeedItemCount2="0" PropertyDatas="48300,48300,48300,289800,9660,9660" SkillTempId="41220401" EquipPetSonTypes="11902,11903"/>
	<PetHallowsTempInfo TemplateId="103037" TemplateName="Fire &amp; Electro Warhammer" HallowType="3" Grades="37" NeedItemCount1="250" NeedItemCount2="0" PropertyDatas="51300,51300,51300,307800,10260,10260" SkillTempId="41220401" EquipPetSonTypes="11902,11903"/>
	<PetHallowsTempInfo TemplateId="103038" TemplateName="Fire &amp; Electro Warhammer" HallowType="3" Grades="38" NeedItemCount1="250" NeedItemCount2="0" PropertyDatas="54300,54300,54300,325800,10860,10860" SkillTempId="41220401" EquipPetSonTypes="11902,11903"/>
	<PetHallowsTempInfo TemplateId="103039" TemplateName="Fire &amp; Electro Warhammer" HallowType="3" Grades="39" NeedItemCount1="250" NeedItemCount2="0" PropertyDatas="57300,57300,57300,343800,11460,11460" SkillTempId="41220401" EquipPetSonTypes="11902,11903"/>
	<PetHallowsTempInfo TemplateId="103040" TemplateName="Fire &amp; Electro Warhammer" HallowType="3" Grades="40" NeedItemCount1="0" NeedItemCount2="1000" PropertyDatas="57300,57300,57300,343800,11460,11460" SkillTempId="41220501" EquipPetSonTypes="11902,11903"/>
	<PetHallowsTempInfo TemplateId="103041" TemplateName="Fire &amp; Electro Warhammer" HallowType="3" Grades="41" NeedItemCount1="300" NeedItemCount2="0" PropertyDatas="60800,60800,60800,364800,12160,12160" SkillTempId="41220501" EquipPetSonTypes="11902,11903"/>
	<PetHallowsTempInfo TemplateId="103042" TemplateName="Fire &amp; Electro Warhammer" HallowType="3" Grades="42" NeedItemCount1="300" NeedItemCount2="0" PropertyDatas="64300,64300,64300,385800,12860,12860" SkillTempId="41220501" EquipPetSonTypes="11902,11903"/>
	<PetHallowsTempInfo TemplateId="103043" TemplateName="Fire &amp; Electro Warhammer" HallowType="3" Grades="43" NeedItemCount1="300" NeedItemCount2="0" PropertyDatas="67800,67800,67800,406800,13560,13560" SkillTempId="41220501" EquipPetSonTypes="11902,11903"/>
	<PetHallowsTempInfo TemplateId="103044" TemplateName="Fire &amp; Electro Warhammer" HallowType="3" Grades="44" NeedItemCount1="300" NeedItemCount2="0" PropertyDatas="71300,71300,71300,427800,14260,14260" SkillTempId="41220501" EquipPetSonTypes="11902,11903"/>
	<PetHallowsTempInfo TemplateId="103045" TemplateName="Fire &amp; Electro Warhammer" HallowType="3" Grades="45" NeedItemCount1="300" NeedItemCount2="0" PropertyDatas="74800,74800,74800,448800,14960,14960" SkillTempId="41220501" EquipPetSonTypes="11902,11903"/>
	<PetHallowsTempInfo TemplateId="103046" TemplateName="Fire &amp; Electro Warhammer" HallowType="3" Grades="46" NeedItemCount1="350" NeedItemCount2="0" PropertyDatas="78800,78800,78800,472800,15760,15760" SkillTempId="41220501" EquipPetSonTypes="11902,11903"/>
	<PetHallowsTempInfo TemplateId="103047" TemplateName="Fire &amp; Electro Warhammer" HallowType="3" Grades="47" NeedItemCount1="350" NeedItemCount2="0" PropertyDatas="82800,82800,82800,496800,16560,16560" SkillTempId="41220501" EquipPetSonTypes="11902,11903"/>
	<PetHallowsTempInfo TemplateId="103048" TemplateName="Fire &amp; Electro Warhammer" HallowType="3" Grades="48" NeedItemCount1="350" NeedItemCount2="0" PropertyDatas="86800,86800,86800,520800,17360,17360" SkillTempId="41220501" EquipPetSonTypes="11902,11903"/>
	<PetHallowsTempInfo TemplateId="103049" TemplateName="Fire &amp; Electro Warhammer" HallowType="3" Grades="49" NeedItemCount1="350" NeedItemCount2="0" PropertyDatas="90800,90800,90800,544800,18160,18160" SkillTempId="41220501" EquipPetSonTypes="11902,11903"/>
	<PetHallowsTempInfo TemplateId="103050" TemplateName="Fire &amp; Electro Warhammer" HallowType="3" Grades="50" NeedItemCount1="0" NeedItemCount2="1000" PropertyDatas="90800,90800,90800,544800,18160,18160" SkillTempId="41220601" EquipPetSonTypes="11902,11903"/>
	<PetHallowsTempInfo TemplateId="103051" TemplateName="Fire &amp; Electro Warhammer" HallowType="3" Grades="51" NeedItemCount1="400" NeedItemCount2="0" PropertyDatas="95800,95800,95800,574800,19160,19160" SkillTempId="41220601" EquipPetSonTypes="11902,11903"/>
	<PetHallowsTempInfo TemplateId="103052" TemplateName="Fire &amp; Electro Warhammer" HallowType="3" Grades="52" NeedItemCount1="400" NeedItemCount2="0" PropertyDatas="100800,100800,100800,604800,20160,20160" SkillTempId="41220601" EquipPetSonTypes="11902,11903"/>
	<PetHallowsTempInfo TemplateId="103053" TemplateName="Fire &amp; Electro Warhammer" HallowType="3" Grades="53" NeedItemCount1="400" NeedItemCount2="0" PropertyDatas="105800,105800,105800,634800,21160,21160" SkillTempId="41220601" EquipPetSonTypes="11902,11903"/>
	<PetHallowsTempInfo TemplateId="103054" TemplateName="Fire &amp; Electro Warhammer" HallowType="3" Grades="54" NeedItemCount1="400" NeedItemCount2="0" PropertyDatas="110800,110800,110800,664800,22160,22160" SkillTempId="41220601" EquipPetSonTypes="11902,11903"/>
	<PetHallowsTempInfo TemplateId="103055" TemplateName="Fire &amp; Electro Warhammer" HallowType="3" Grades="55" NeedItemCount1="400" NeedItemCount2="0" PropertyDatas="115800,115800,115800,694800,23160,23160" SkillTempId="41220601" EquipPetSonTypes="11902,11903"/>
	<PetHallowsTempInfo TemplateId="103056" TemplateName="Fire &amp; Electro Warhammer" HallowType="3" Grades="56" NeedItemCount1="400" NeedItemCount2="0" PropertyDatas="120800,120800,120800,724800,24160,24160" SkillTempId="41220601" EquipPetSonTypes="11902,11903"/>
	<PetHallowsTempInfo TemplateId="103057" TemplateName="Fire &amp; Electro Warhammer" HallowType="3" Grades="57" NeedItemCount1="400" NeedItemCount2="0" PropertyDatas="125800,125800,125800,754800,25160,25160" SkillTempId="41220601" EquipPetSonTypes="11902,11903"/>
	<PetHallowsTempInfo TemplateId="103058" TemplateName="Fire &amp; Electro Warhammer" HallowType="3" Grades="58" NeedItemCount1="400" NeedItemCount2="0" PropertyDatas="130800,130800,130800,784800,26160,26160" SkillTempId="41220601" EquipPetSonTypes="11902,11903"/>
	<PetHallowsTempInfo TemplateId="103059" TemplateName="Fire &amp; Electro Warhammer" HallowType="3" Grades="59" NeedItemCount1="400" NeedItemCount2="0" PropertyDatas="135800,135800,135800,814800,27160,27160" SkillTempId="41220601" EquipPetSonTypes="11902,11903"/>
	<PetHallowsTempInfo TemplateId="103060" TemplateName="Fire &amp; Electro Warhammer" HallowType="3" Grades="60" NeedItemCount1="0" NeedItemCount2="2000" PropertyDatas="135800,135800,135800,814800,27160,27160" SkillTempId="41220701" EquipPetSonTypes="11902,11903"/>
	<PetHallowsTempInfo TemplateId="103061" TemplateName="Fire &amp; Electro Warhammer" HallowType="3" Grades="61" NeedItemCount1="500" NeedItemCount2="0" PropertyDatas="140800,140800,140800,844800,28160,28160" SkillTempId="41220701" EquipPetSonTypes="11902,11903"/>
	<PetHallowsTempInfo TemplateId="103062" TemplateName="Fire &amp; Electro Warhammer" HallowType="3" Grades="62" NeedItemCount1="500" NeedItemCount2="0" PropertyDatas="145800,145800,145800,874800,29160,29160" SkillTempId="41220701" EquipPetSonTypes="11902,11903"/>
	<PetHallowsTempInfo TemplateId="103063" TemplateName="Fire &amp; Electro Warhammer" HallowType="3" Grades="63" NeedItemCount1="500" NeedItemCount2="0" PropertyDatas="150800,150800,150800,904800,30160,30160" SkillTempId="41220701" EquipPetSonTypes="11902,11903"/>
	<PetHallowsTempInfo TemplateId="103064" TemplateName="Fire &amp; Electro Warhammer" HallowType="3" Grades="64" NeedItemCount1="500" NeedItemCount2="0" PropertyDatas="155800,155800,155800,934800,31160,31160" SkillTempId="41220701" EquipPetSonTypes="11902,11903"/>
	<PetHallowsTempInfo TemplateId="103065" TemplateName="Fire &amp; Electro Warhammer" HallowType="3" Grades="65" NeedItemCount1="500" NeedItemCount2="0" PropertyDatas="160800,160800,160800,964800,32160,32160" SkillTempId="41220701" EquipPetSonTypes="11902,11903"/>
	<PetHallowsTempInfo TemplateId="103066" TemplateName="Fire &amp; Electro Warhammer" HallowType="3" Grades="66" NeedItemCount1="650" NeedItemCount2="0" PropertyDatas="165800,165800,165800,994800,33160,33160" SkillTempId="41220701" EquipPetSonTypes="11902,11903"/>
	<PetHallowsTempInfo TemplateId="103067" TemplateName="Fire &amp; Electro Warhammer" HallowType="3" Grades="67" NeedItemCount1="650" NeedItemCount2="0" PropertyDatas="170800,170800,170800,1024800,34160,34160" SkillTempId="41220701" EquipPetSonTypes="11902,11903"/>
	<PetHallowsTempInfo TemplateId="103068" TemplateName="Fire &amp; Electro Warhammer" HallowType="3" Grades="68" NeedItemCount1="650" NeedItemCount2="0" PropertyDatas="175800,175800,175800,1054800,35160,35160" SkillTempId="41220701" EquipPetSonTypes="11902,11903"/>
	<PetHallowsTempInfo TemplateId="103069" TemplateName="Fire &amp; Electro Warhammer" HallowType="3" Grades="69" NeedItemCount1="650" NeedItemCount2="0" PropertyDatas="180800,180800,180800,1084800,36160,36160" SkillTempId="41220701" EquipPetSonTypes="11902,11903"/>
	<PetHallowsTempInfo TemplateId="103070" TemplateName="Fire &amp; Electro Warhammer" HallowType="3" Grades="70" NeedItemCount1="0" NeedItemCount2="2000" PropertyDatas="180800,180800,180800,1084800,36160,36160" SkillTempId="41220801" EquipPetSonTypes="11902,11903"/>
	<PetHallowsTempInfo TemplateId="103071" TemplateName="Fire &amp; Electro Warhammer" HallowType="3" Grades="71" NeedItemCount1="800" NeedItemCount2="0" PropertyDatas="185800,185800,185800,1114800,37160,37160" SkillTempId="41220801" EquipPetSonTypes="11902,11903"/>
	<PetHallowsTempInfo TemplateId="103072" TemplateName="Fire &amp; Electro Warhammer" HallowType="3" Grades="72" NeedItemCount1="800" NeedItemCount2="0" PropertyDatas="190800,190800,190800,1144800,38160,38160" SkillTempId="41220801" EquipPetSonTypes="11902,11903"/>
	<PetHallowsTempInfo TemplateId="103073" TemplateName="Fire &amp; Electro Warhammer" HallowType="3" Grades="73" NeedItemCount1="800" NeedItemCount2="0" PropertyDatas="195800,195800,195800,1174800,39160,39160" SkillTempId="41220801" EquipPetSonTypes="11902,11903"/>
	<PetHallowsTempInfo TemplateId="103074" TemplateName="Fire &amp; Electro Warhammer" HallowType="3" Grades="74" NeedItemCount1="800" NeedItemCount2="0" PropertyDatas="200800,200800,200800,1204800,40160,40160" SkillTempId="41220801" EquipPetSonTypes="11902,11903"/>
	<PetHallowsTempInfo TemplateId="103075" TemplateName="Fire &amp; Electro Warhammer" HallowType="3" Grades="75" NeedItemCount1="800" NeedItemCount2="0" PropertyDatas="205800,205800,205800,1234800,41160,41160" SkillTempId="41220801" EquipPetSonTypes="11902,11903"/>
	<PetHallowsTempInfo TemplateId="103076" TemplateName="Fire &amp; Electro Warhammer" HallowType="3" Grades="76" NeedItemCount1="1000" NeedItemCount2="0" PropertyDatas="210800,210800,210800,1264800,42160,42160" SkillTempId="41220801" EquipPetSonTypes="11902,11903"/>
	<PetHallowsTempInfo TemplateId="103077" TemplateName="Fire &amp; Electro Warhammer" HallowType="3" Grades="77" NeedItemCount1="1000" NeedItemCount2="0" PropertyDatas="215800,215800,215800,1294800,43160,43160" SkillTempId="41220801" EquipPetSonTypes="11902,11903"/>
	<PetHallowsTempInfo TemplateId="103078" TemplateName="Fire &amp; Electro Warhammer" HallowType="3" Grades="78" NeedItemCount1="1000" NeedItemCount2="0" PropertyDatas="220800,220800,220800,1324800,44160,44160" SkillTempId="41220801" EquipPetSonTypes="11902,11903"/>
	<PetHallowsTempInfo TemplateId="103079" TemplateName="Fire &amp; Electro Warhammer" HallowType="3" Grades="79" NeedItemCount1="1000" NeedItemCount2="0" PropertyDatas="225800,225800,225800,1354800,45160,45160" SkillTempId="41220801" EquipPetSonTypes="11902,11903"/>
	<PetHallowsTempInfo TemplateId="103080" TemplateName="Fire &amp; Electro Warhammer" HallowType="3" Grades="80" NeedItemCount1="0" NeedItemCount2="4000" PropertyDatas="225800,225800,225800,1354800,45160,45160" SkillTempId="41220901" EquipPetSonTypes="11902,11903"/>
	<PetHallowsTempInfo TemplateId="103081" TemplateName="Fire &amp; Electro Warhammer" HallowType="3" Grades="81" NeedItemCount1="1500" NeedItemCount2="0" PropertyDatas="230800,230800,230800,1384800,46160,46160" SkillTempId="41220901" EquipPetSonTypes="11902,11903"/>
	<PetHallowsTempInfo TemplateId="103082" TemplateName="Fire &amp; Electro Warhammer" HallowType="3" Grades="82" NeedItemCount1="1500" NeedItemCount2="0" PropertyDatas="235800,235800,235800,1414800,47160,47160" SkillTempId="41220901" EquipPetSonTypes="11902,11903"/>
	<PetHallowsTempInfo TemplateId="103083" TemplateName="Fire &amp; Electro Warhammer" HallowType="3" Grades="83" NeedItemCount1="1500" NeedItemCount2="0" PropertyDatas="240800,240800,240800,1444800,48160,48160" SkillTempId="41220901" EquipPetSonTypes="11902,11903"/>
	<PetHallowsTempInfo TemplateId="103084" TemplateName="Fire &amp; Electro Warhammer" HallowType="3" Grades="84" NeedItemCount1="1500" NeedItemCount2="0" PropertyDatas="245800,245800,245800,1474800,49160,49160" SkillTempId="41220901" EquipPetSonTypes="11902,11903"/>
	<PetHallowsTempInfo TemplateId="103085" TemplateName="Fire &amp; Electro Warhammer" HallowType="3" Grades="85" NeedItemCount1="1500" NeedItemCount2="0" PropertyDatas="250800,250800,250800,1504800,50160,50160" SkillTempId="41220901" EquipPetSonTypes="11902,11903"/>
	<PetHallowsTempInfo TemplateId="103086" TemplateName="Fire &amp; Electro Warhammer" HallowType="3" Grades="86" NeedItemCount1="1500" NeedItemCount2="0" PropertyDatas="255800,255800,255800,1534800,51160,51160" SkillTempId="41220901" EquipPetSonTypes="11902,11903"/>
	<PetHallowsTempInfo TemplateId="103087" TemplateName="Fire &amp; Electro Warhammer" HallowType="3" Grades="87" NeedItemCount1="1500" NeedItemCount2="0" PropertyDatas="260800,260800,260800,1564800,52160,52160" SkillTempId="41220901" EquipPetSonTypes="11902,11903"/>
	<PetHallowsTempInfo TemplateId="103088" TemplateName="Fire &amp; Electro Warhammer" HallowType="3" Grades="88" NeedItemCount1="1500" NeedItemCount2="0" PropertyDatas="265800,265800,265800,1594800,53160,53160" SkillTempId="41220901" EquipPetSonTypes="11902,11903"/>
	<PetHallowsTempInfo TemplateId="103089" TemplateName="Fire &amp; Electro Warhammer" HallowType="3" Grades="89" NeedItemCount1="1500" NeedItemCount2="0" PropertyDatas="270800,270800,270800,1624800,54160,54160" SkillTempId="41220901" EquipPetSonTypes="11902,11903"/>
	<PetHallowsTempInfo TemplateId="103090" TemplateName="Fire &amp; Electro Warhammer" HallowType="3" Grades="90" NeedItemCount1="0" NeedItemCount2="5000" PropertyDatas="270800,270800,270800,1624800,54160,54160" SkillTempId="41221001" EquipPetSonTypes="11902,11903"/>
	<PetHallowsTempInfo TemplateId="103091" TemplateName="Fire &amp; Electro Warhammer" HallowType="3" Grades="91" NeedItemCount1="2000" NeedItemCount2="0" PropertyDatas="275800,275800,275800,1654800,55160,55160" SkillTempId="41221001" EquipPetSonTypes="11902,11903"/>
	<PetHallowsTempInfo TemplateId="103092" TemplateName="Fire &amp; Electro Warhammer" HallowType="3" Grades="92" NeedItemCount1="2000" NeedItemCount2="0" PropertyDatas="280800,280800,280800,1684800,56160,56160" SkillTempId="41221001" EquipPetSonTypes="11902,11903"/>
	<PetHallowsTempInfo TemplateId="103093" TemplateName="Fire &amp; Electro Warhammer" HallowType="3" Grades="93" NeedItemCount1="2000" NeedItemCount2="0" PropertyDatas="285800,285800,285800,1714800,57160,57160" SkillTempId="41221001" EquipPetSonTypes="11902,11903"/>
	<PetHallowsTempInfo TemplateId="103094" TemplateName="Fire &amp; Electro Warhammer" HallowType="3" Grades="94" NeedItemCount1="2000" NeedItemCount2="0" PropertyDatas="290800,290800,290800,1744800,58160,58160" SkillTempId="41221001" EquipPetSonTypes="11902,11903"/>
	<PetHallowsTempInfo TemplateId="103095" TemplateName="Fire &amp; Electro Warhammer" HallowType="3" Grades="95" NeedItemCount1="2000" NeedItemCount2="0" PropertyDatas="295800,295800,295800,1774800,59160,59160" SkillTempId="41221001" EquipPetSonTypes="11902,11903"/>
	<PetHallowsTempInfo TemplateId="103096" TemplateName="Fire &amp; Electro Warhammer" HallowType="3" Grades="96" NeedItemCount1="2000" NeedItemCount2="0" PropertyDatas="300800,300800,300800,1804800,60160,60160" SkillTempId="41221001" EquipPetSonTypes="11902,11903"/>
	<PetHallowsTempInfo TemplateId="103097" TemplateName="Fire &amp; Electro Warhammer" HallowType="3" Grades="97" NeedItemCount1="2000" NeedItemCount2="0" PropertyDatas="305800,305800,305800,1834800,61160,61160" SkillTempId="41221001" EquipPetSonTypes="11902,11903"/>
	<PetHallowsTempInfo TemplateId="103098" TemplateName="Fire &amp; Electro Warhammer" HallowType="3" Grades="98" NeedItemCount1="2000" NeedItemCount2="0" PropertyDatas="310800,310800,310800,1864800,62160,62160" SkillTempId="41221001" EquipPetSonTypes="11902,11903"/>
	<PetHallowsTempInfo TemplateId="103099" TemplateName="Fire &amp; Electro Warhammer" HallowType="3" Grades="99" NeedItemCount1="2000" NeedItemCount2="0" PropertyDatas="315800,315800,315800,1894800,63160,63160" SkillTempId="41221001" EquipPetSonTypes="11902,11903"/>
</PetHallowsTempInfos>