<!--
	Might be related to Lord's Trials
-->
<SignDrop>
	<SignDropInfo DropId="17001" Times="2" TemplateId="2131521" Data="5" ValidDate="0"/>
	<SignDropInfo DropId="17001" Times="2" TemplateId="212018" Data="2" ValidDate="0"/>
	<SignDropInfo DropId="17001" Times="2" TemplateId="2240602" Data="1" ValidDate="0"/>
	<SignDropInfo DropId="17001" Times="2" TemplateId="2030102" Data="1" ValidDate="0"/>
	<SignDropInfo DropId="17001" Times="2" TemplateId="250001" Data="15" ValidDate="0"/>
	<SignDropInfo DropId="17002" Times="5" TemplateId="2240602" Data="2" ValidDate="0"/>
	<SignDropInfo DropId="17002" Times="5" TemplateId="2030102" Data="2" ValidDate="0"/>
	<SignDropInfo DropId="17002" Times="5" TemplateId="250001" Data="20" ValidDate="0"/>
	<SignDropInfo DropId="17002" Times="5" TemplateId="-500" Data="20" ValidDate="0"/>
	<SignDropInfo DropId="17002" Times="5" TemplateId="2131521" Data="8" ValidDate="0"/>
	<SignDropInfo DropId="17002" Times="5" TemplateId="212018" Data="5" ValidDate="0"/>
	<SignDropInfo DropId="17003" Times="8" TemplateId="-500" Data="50" ValidDate="0"/>
	<SignDropInfo DropId="17003" Times="8" TemplateId="2131521" Data="10" ValidDate="0"/>
	<SignDropInfo DropId="17003" Times="8" TemplateId="212018" Data="8" ValidDate="0"/>
	<SignDropInfo DropId="17003" Times="8" TemplateId="2240602" Data="3" ValidDate="0"/>
	<SignDropInfo DropId="17003" Times="8" TemplateId="2030102" Data="3" ValidDate="0"/>
	<SignDropInfo DropId="17003" Times="8" TemplateId="250001" Data="25" ValidDate="0"/>
	<SignDropInfo DropId="17004" Times="10" TemplateId="2030102" Data="5" ValidDate="0"/>
	<SignDropInfo DropId="17004" Times="10" TemplateId="250001" Data="30" ValidDate="0"/>
	<SignDropInfo DropId="17004" Times="10" TemplateId="-500" Data="100" ValidDate="0"/>
	<SignDropInfo DropId="17004" Times="10" TemplateId="2131521" Data="12" ValidDate="0"/>
	<SignDropInfo DropId="17004" Times="10" TemplateId="212018" Data="10" ValidDate="0"/>
	<SignDropInfo DropId="17004" Times="10" TemplateId="2240603" Data="1" ValidDate="0"/>
</SignDrop>