<SevenYearRewardDrop>
	<SevenYearRewardDropInfo id="0" dropId="0" site="86" para2="0" itemId="0" count="0" isBind="0" appearType="0" validDate="0" isShow="0"/>
	<SevenYearRewardDropInfo id="0" dropId="0" site="499" para2="0" itemId="0" count="0" isBind="0" appearType="0" validDate="0" isShow="0"/>
	<SevenYearRewardDropInfo id="0" dropId="0" site="116" para2="0" itemId="0" count="0" isBind="0" appearType="0" validDate="0" isShow="0"/>
	<SevenYearRewardDropInfo id="0" dropId="0" site="488" para2="0" itemId="0" count="0" isBind="0" appearType="0" validDate="0" isShow="0"/>
	<SevenYearRewardDropInfo id="0" dropId="0" site="424" para2="0" itemId="0" count="0" isBind="0" appearType="0" validDate="0" isShow="0"/>
	<SevenYearRewardDropInfo id="0" dropId="0" site="296" para2="0" itemId="0" count="0" isBind="0" appearType="0" validDate="0" isShow="0"/>
	<SevenYearRewardDropInfo id="0" dropId="0" site="232" para2="0" itemId="0" count="0" isBind="0" appearType="0" validDate="0" isShow="0"/>
	<SevenYearRewardDropInfo id="0" dropId="0" site="168" para2="0" itemId="0" count="0" isBind="0" appearType="0" validDate="0" isShow="0"/>
	<SevenYearRewardDropInfo id="0" dropId="0" site="106" para2="0" itemId="0" count="0" isBind="0" appearType="0" validDate="0" isShow="0"/>
	<SevenYearRewardDropInfo id="0" dropId="0" site="456" para2="0" itemId="0" count="0" isBind="0" appearType="0" validDate="0" isShow="0"/>
	<SevenYearRewardDropInfo id="0" dropId="0" site="392" para2="0" itemId="0" count="0" isBind="0" appearType="0" validDate="0" isShow="0"/>
	<SevenYearRewardDropInfo id="0" dropId="0" site="328" para2="0" itemId="0" count="0" isBind="0" appearType="0" validDate="0" isShow="0"/>
	<SevenYearRewardDropInfo id="0" dropId="0" site="264" para2="0" itemId="0" count="0" isBind="0" appearType="0" validDate="0" isShow="0"/>
	<SevenYearRewardDropInfo id="0" dropId="0" site="136" para2="0" itemId="0" count="0" isBind="0" appearType="0" validDate="0" isShow="0"/>
	<SevenYearRewardDropInfo id="0" dropId="0" site="381" para2="0" itemId="0" count="0" isBind="0" appearType="0" validDate="0" isShow="0"/>
	<SevenYearRewardDropInfo id="0" dropId="0" site="317" para2="0" itemId="0" count="0" isBind="0" appearType="0" validDate="0" isShow="0"/>
	<SevenYearRewardDropInfo id="0" dropId="0" site="253" para2="0" itemId="0" count="0" isBind="0" appearType="0" validDate="0" isShow="0"/>
	<SevenYearRewardDropInfo id="0" dropId="0" site="189" para2="0" itemId="0" count="0" isBind="0" appearType="0" validDate="0" isShow="0"/>
	<SevenYearRewardDropInfo id="0" dropId="0" site="477" para2="0" itemId="0" count="0" isBind="0" appearType="0" validDate="0" isShow="0"/>
	<SevenYearRewardDropInfo id="0" dropId="0" site="413" para2="0" itemId="0" count="0" isBind="0" appearType="0" validDate="0" isShow="0"/>
	<SevenYearRewardDropInfo id="0" dropId="0" site="349" para2="0" itemId="0" count="0" isBind="0" appearType="0" validDate="0" isShow="0"/>
	<SevenYearRewardDropInfo id="0" dropId="0" site="221" para2="0" itemId="0" count="0" isBind="0" appearType="0" validDate="0" isShow="0"/>
	<SevenYearRewardDropInfo id="0" dropId="0" site="157" para2="0" itemId="0" count="0" isBind="0" appearType="0" validDate="0" isShow="0"/>
	<SevenYearRewardDropInfo id="0" dropId="0" site="466" para2="0" itemId="0" count="0" isBind="0" appearType="0" validDate="0" isShow="0"/>
	<SevenYearRewardDropInfo id="0" dropId="0" site="402" para2="0" itemId="0" count="0" isBind="0" appearType="0" validDate="0" isShow="0"/>
	<SevenYearRewardDropInfo id="0" dropId="0" site="338" para2="0" itemId="0" count="0" isBind="0" appearType="0" validDate="0" isShow="0"/>
	<SevenYearRewardDropInfo id="0" dropId="0" site="274" para2="0" itemId="0" count="0" isBind="0" appearType="0" validDate="0" isShow="0"/>
	<SevenYearRewardDropInfo id="0" dropId="0" site="146" para2="0" itemId="0" count="0" isBind="0" appearType="0" validDate="0" isShow="0"/>
	<SevenYearRewardDropInfo id="0" dropId="0" site="498" para2="0" itemId="0" count="0" isBind="0" appearType="0" validDate="0" isShow="0"/>
	<SevenYearRewardDropInfo id="0" dropId="0" site="434" para2="0" itemId="0" count="0" isBind="0" appearType="0" validDate="0" isShow="0"/>
	<SevenYearRewardDropInfo id="0" dropId="0" site="306" para2="0" itemId="0" count="0" isBind="0" appearType="0" validDate="0" isShow="0"/>
	<SevenYearRewardDropInfo id="0" dropId="0" site="242" para2="0" itemId="0" count="0" isBind="0" appearType="0" validDate="0" isShow="0"/>
	<SevenYearRewardDropInfo id="0" dropId="0" site="178" para2="0" itemId="0" count="0" isBind="0" appearType="0" validDate="0" isShow="0"/>
	<SevenYearRewardDropInfo id="0" dropId="0" site="444" para2="0" itemId="0" count="0" isBind="0" appearType="0" validDate="0" isShow="0"/>
	<SevenYearRewardDropInfo id="0" dropId="0" site="316" para2="0" itemId="0" count="0" isBind="0" appearType="0" validDate="0" isShow="0"/>
	<SevenYearRewardDropInfo id="0" dropId="0" site="252" para2="0" itemId="0" count="0" isBind="0" appearType="0" validDate="0" isShow="0"/>
	<SevenYearRewardDropInfo id="0" dropId="0" site="188" para2="0" itemId="0" count="0" isBind="0" appearType="0" validDate="0" isShow="0"/>
	<SevenYearRewardDropInfo id="0" dropId="0" site="124" para2="0" itemId="0" count="0" isBind="0" appearType="0" validDate="0" isShow="0"/>
	<SevenYearRewardDropInfo id="0" dropId="0" site="476" para2="0" itemId="0" count="0" isBind="0" appearType="0" validDate="0" isShow="0"/>
	<SevenYearRewardDropInfo id="0" dropId="0" site="412" para2="0" itemId="0" count="0" isBind="0" appearType="0" validDate="0" isShow="0"/>
	<SevenYearRewardDropInfo id="0" dropId="0" site="348" para2="0" itemId="0" count="0" isBind="0" appearType="0" validDate="0" isShow="0"/>
	<SevenYearRewardDropInfo id="0" dropId="0" site="284" para2="0" itemId="0" count="0" isBind="0" appearType="0" validDate="0" isShow="0"/>
	<SevenYearRewardDropInfo id="0" dropId="0" site="156" para2="0" itemId="0" count="0" isBind="0" appearType="0" validDate="0" isShow="0"/>
	<SevenYearRewardDropInfo id="0" dropId="0" site="94" para2="0" itemId="0" count="0" isBind="0" appearType="0" validDate="0" isShow="0"/>
	<SevenYearRewardDropInfo id="0" dropId="0" site="401" para2="0" itemId="0" count="0" isBind="0" appearType="0" validDate="0" isShow="0"/>
	<SevenYearRewardDropInfo id="0" dropId="0" site="337" para2="0" itemId="0" count="0" isBind="0" appearType="0" validDate="0" isShow="0"/>
	<SevenYearRewardDropInfo id="0" dropId="0" site="273" para2="0" itemId="0" count="0" isBind="0" appearType="0" validDate="0" isShow="0"/>
	<SevenYearRewardDropInfo id="0" dropId="0" site="209" para2="0" itemId="0" count="0" isBind="0" appearType="0" validDate="0" isShow="0"/>
	<SevenYearRewardDropInfo id="0" dropId="0" site="84" para2="0" itemId="0" count="0" isBind="0" appearType="0" validDate="0" isShow="0"/>
	<SevenYearRewardDropInfo id="0" dropId="0" site="497" para2="0" itemId="0" count="0" isBind="0" appearType="0" validDate="0" isShow="0"/>
	<SevenYearRewardDropInfo id="0" dropId="0" site="433" para2="0" itemId="0" count="0" isBind="0" appearType="0" validDate="0" isShow="0"/>
	<SevenYearRewardDropInfo id="0" dropId="0" site="369" para2="0" itemId="0" count="0" isBind="0" appearType="0" validDate="0" isShow="0"/>
	<SevenYearRewardDropInfo id="0" dropId="0" site="241" para2="0" itemId="0" count="0" isBind="0" appearType="0" validDate="0" isShow="0"/>
	<SevenYearRewardDropInfo id="0" dropId="0" site="177" para2="0" itemId="0" count="0" isBind="0" appearType="0" validDate="0" isShow="0"/>
	<SevenYearRewardDropInfo id="0" dropId="0" site="114" para2="0" itemId="0" count="0" isBind="0" appearType="0" validDate="0" isShow="0"/>
	<SevenYearRewardDropInfo id="0" dropId="0" site="486" para2="0" itemId="0" count="0" isBind="0" appearType="0" validDate="0" isShow="0"/>
	<SevenYearRewardDropInfo id="0" dropId="0" site="422" para2="0" itemId="0" count="0" isBind="0" appearType="0" validDate="0" isShow="0"/>
	<SevenYearRewardDropInfo id="0" dropId="0" site="358" para2="0" itemId="0" count="0" isBind="0" appearType="0" validDate="0" isShow="0"/>
	<SevenYearRewardDropInfo id="0" dropId="0" site="294" para2="0" itemId="0" count="0" isBind="0" appearType="0" validDate="0" isShow="0"/>
	<SevenYearRewardDropInfo id="0" dropId="0" site="166" para2="0" itemId="0" count="0" isBind="0" appearType="0" validDate="0" isShow="0"/>
	<SevenYearRewardDropInfo id="0" dropId="0" site="104" para2="0" itemId="0" count="0" isBind="0" appearType="0" validDate="0" isShow="0"/>
	<SevenYearRewardDropInfo id="0" dropId="0" site="454" para2="0" itemId="0" count="0" isBind="0" appearType="0" validDate="0" isShow="0"/>
	<SevenYearRewardDropInfo id="0" dropId="0" site="326" para2="0" itemId="0" count="0" isBind="0" appearType="0" validDate="0" isShow="0"/>
	<SevenYearRewardDropInfo id="0" dropId="0" site="262" para2="0" itemId="0" count="0" isBind="0" appearType="0" validDate="0" isShow="0"/>
	<SevenYearRewardDropInfo id="0" dropId="0" site="198" para2="0" itemId="0" count="0" isBind="0" appearType="0" validDate="0" isShow="0"/>
	<SevenYearRewardDropInfo id="0" dropId="0" site="134" para2="0" itemId="0" count="0" isBind="0" appearType="0" validDate="0" isShow="0"/>
	<SevenYearRewardDropInfo id="0" dropId="0" site="464" para2="0" itemId="0" count="0" isBind="0" appearType="0" validDate="0" isShow="0"/>
	<SevenYearRewardDropInfo id="0" dropId="0" site="336" para2="0" itemId="0" count="0" isBind="0" appearType="0" validDate="0" isShow="0"/>
	<SevenYearRewardDropInfo id="0" dropId="0" site="272" para2="0" itemId="0" count="0" isBind="0" appearType="0" validDate="0" isShow="0"/>
	<SevenYearRewardDropInfo id="0" dropId="0" site="208" para2="0" itemId="0" count="0" isBind="0" appearType="0" validDate="0" isShow="0"/>
	<SevenYearRewardDropInfo id="0" dropId="0" site="144" para2="0" itemId="0" count="0" isBind="0" appearType="0" validDate="0" isShow="0"/>
	<SevenYearRewardDropInfo id="0" dropId="0" site="496" para2="0" itemId="0" count="0" isBind="0" appearType="0" validDate="0" isShow="0"/>
	<SevenYearRewardDropInfo id="0" dropId="0" site="432" para2="0" itemId="0" count="0" isBind="0" appearType="0" validDate="0" isShow="0"/>
	<SevenYearRewardDropInfo id="0" dropId="0" site="368" para2="0" itemId="0" count="0" isBind="0" appearType="0" validDate="0" isShow="0"/>
	<SevenYearRewardDropInfo id="0" dropId="0" site="304" para2="0" itemId="0" count="0" isBind="0" appearType="0" validDate="0" isShow="0"/>
	<SevenYearRewardDropInfo id="0" dropId="0" site="176" para2="0" itemId="0" count="0" isBind="0" appearType="0" validDate="0" isShow="0"/>
	<SevenYearRewardDropInfo id="0" dropId="0" site="113" para2="0" itemId="0" count="0" isBind="0" appearType="0" validDate="0" isShow="0"/>
	<SevenYearRewardDropInfo id="0" dropId="0" site="421" para2="0" itemId="0" count="0" isBind="0" appearType="0" validDate="0" isShow="0"/>
	<SevenYearRewardDropInfo id="0" dropId="0" site="357" para2="0" itemId="0" count="0" isBind="0" appearType="0" validDate="0" isShow="0"/>
	<SevenYearRewardDropInfo id="0" dropId="0" site="293" para2="0" itemId="0" count="0" isBind="0" appearType="0" validDate="0" isShow="0"/>
	<SevenYearRewardDropInfo id="0" dropId="0" site="229" para2="0" itemId="0" count="0" isBind="0" appearType="0" validDate="0" isShow="0"/>
	<SevenYearRewardDropInfo id="0" dropId="0" site="453" para2="0" itemId="0" count="0" isBind="0" appearType="0" validDate="0" isShow="0"/>
	<SevenYearRewardDropInfo id="0" dropId="0" site="389" para2="0" itemId="0" count="0" isBind="0" appearType="0" validDate="0" isShow="0"/>
	<SevenYearRewardDropInfo id="0" dropId="0" site="261" para2="0" itemId="0" count="0" isBind="0" appearType="0" validDate="0" isShow="0"/>
	<SevenYearRewardDropInfo id="0" dropId="0" site="197" para2="0" itemId="0" count="0" isBind="0" appearType="0" validDate="0" isShow="0"/>
	<SevenYearRewardDropInfo id="0" dropId="0" site="133" para2="0" itemId="0" count="0" isBind="0" appearType="0" validDate="0" isShow="0"/>
	<SevenYearRewardDropInfo id="0" dropId="0" site="442" para2="0" itemId="0" count="0" isBind="0" appearType="0" validDate="0" isShow="0"/>
	<SevenYearRewardDropInfo id="0" dropId="0" site="378" para2="0" itemId="0" count="0" isBind="0" appearType="0" validDate="0" isShow="0"/>
	<SevenYearRewardDropInfo id="0" dropId="0" site="314" para2="0" itemId="0" count="0" isBind="0" appearType="0" validDate="0" isShow="0"/>
	<SevenYearRewardDropInfo id="0" dropId="0" site="186" para2="0" itemId="0" count="0" isBind="0" appearType="0" validDate="0" isShow="0"/>
	<SevenYearRewardDropInfo id="0" dropId="0" site="122" para2="0" itemId="0" count="0" isBind="0" appearType="0" validDate="0" isShow="0"/>
	<SevenYearRewardDropInfo id="0" dropId="0" site="474" para2="0" itemId="0" count="0" isBind="0" appearType="0" validDate="0" isShow="0"/>
	<SevenYearRewardDropInfo id="0" dropId="0" site="346" para2="0" itemId="0" count="0" isBind="0" appearType="0" validDate="0" isShow="0"/>
	<SevenYearRewardDropInfo id="0" dropId="0" site="282" para2="0" itemId="0" count="0" isBind="0" appearType="0" validDate="0" isShow="0"/>
	<SevenYearRewardDropInfo id="0" dropId="0" site="218" para2="0" itemId="0" count="0" isBind="0" appearType="0" validDate="0" isShow="0"/>
	<SevenYearRewardDropInfo id="0" dropId="0" site="154" para2="0" itemId="0" count="0" isBind="0" appearType="0" validDate="0" isShow="0"/>
	<SevenYearRewardDropInfo id="0" dropId="0" site="92" para2="0" itemId="0" count="0" isBind="0" appearType="0" validDate="0" isShow="0"/>
	<SevenYearRewardDropInfo id="0" dropId="0" site="82" para2="0" itemId="0" count="0" isBind="0" appearType="0" validDate="0" isShow="0"/>
	<SevenYearRewardDropInfo id="0" dropId="0" site="112" para2="0" itemId="0" count="0" isBind="0" appearType="0" validDate="0" isShow="0"/>
	<SevenYearRewardDropInfo id="0" dropId="0" site="356" para2="0" itemId="0" count="0" isBind="0" appearType="0" validDate="0" isShow="0"/>
	<SevenYearRewardDropInfo id="0" dropId="0" site="292" para2="0" itemId="0" count="0" isBind="0" appearType="0" validDate="0" isShow="0"/>
	<SevenYearRewardDropInfo id="0" dropId="0" site="228" para2="0" itemId="0" count="0" isBind="0" appearType="0" validDate="0" isShow="0"/>
	<SevenYearRewardDropInfo id="0" dropId="0" site="164" para2="0" itemId="0" count="0" isBind="0" appearType="0" validDate="0" isShow="0"/>
	<SevenYearRewardDropInfo id="0" dropId="0" site="102" para2="0" itemId="0" count="0" isBind="0" appearType="0" validDate="0" isShow="0"/>
	<SevenYearRewardDropInfo id="0" dropId="0" site="452" para2="0" itemId="0" count="0" isBind="0" appearType="0" validDate="0" isShow="0"/>
	<SevenYearRewardDropInfo id="0" dropId="0" site="388" para2="0" itemId="0" count="0" isBind="0" appearType="0" validDate="0" isShow="0"/>
	<SevenYearRewardDropInfo id="0" dropId="0" site="324" para2="0" itemId="0" count="0" isBind="0" appearType="0" validDate="0" isShow="0"/>
	<SevenYearRewardDropInfo id="0" dropId="0" site="196" para2="0" itemId="0" count="0" isBind="0" appearType="0" validDate="0" isShow="0"/>
	<SevenYearRewardDropInfo id="0" dropId="0" site="132" para2="0" itemId="0" count="0" isBind="0" appearType="0" validDate="0" isShow="0"/>
	<SevenYearRewardDropInfo id="0" dropId="0" site="484" para2="0" itemId="0" count="0" isBind="0" appearType="0" validDate="0" isShow="0"/>
	<SevenYearRewardDropInfo id="0" dropId="0" site="377" para2="0" itemId="0" count="0" isBind="0" appearType="0" validDate="0" isShow="0"/>
	<SevenYearRewardDropInfo id="0" dropId="0" site="313" para2="0" itemId="0" count="0" isBind="0" appearType="0" validDate="0" isShow="0"/>
	<SevenYearRewardDropInfo id="0" dropId="0" site="249" para2="0" itemId="0" count="0" isBind="0" appearType="0" validDate="0" isShow="0"/>
	<SevenYearRewardDropInfo id="0" dropId="0" site="121" para2="0" itemId="0" count="0" isBind="0" appearType="0" validDate="0" isShow="0"/>
	<SevenYearRewardDropInfo id="0" dropId="0" site="473" para2="0" itemId="0" count="0" isBind="0" appearType="0" validDate="0" isShow="0"/>
	<SevenYearRewardDropInfo id="0" dropId="0" site="409" para2="0" itemId="0" count="0" isBind="0" appearType="0" validDate="0" isShow="0"/>
	<SevenYearRewardDropInfo id="0" dropId="0" site="281" para2="0" itemId="0" count="0" isBind="0" appearType="0" validDate="0" isShow="0"/>
	<SevenYearRewardDropInfo id="0" dropId="0" site="217" para2="0" itemId="0" count="0" isBind="0" appearType="0" validDate="0" isShow="0"/>
	<SevenYearRewardDropInfo id="0" dropId="0" site="153" para2="0" itemId="0" count="0" isBind="0" appearType="0" validDate="0" isShow="0"/>
	<SevenYearRewardDropInfo id="0" dropId="0" site="441" para2="0" itemId="0" count="0" isBind="0" appearType="0" validDate="0" isShow="0"/>
	<SevenYearRewardDropInfo id="0" dropId="0" site="334" para2="0" itemId="0" count="0" isBind="0" appearType="0" validDate="0" isShow="0"/>
	<SevenYearRewardDropInfo id="0" dropId="0" site="206" para2="0" itemId="0" count="0" isBind="0" appearType="0" validDate="0" isShow="0"/>
	<SevenYearRewardDropInfo id="0" dropId="0" site="142" para2="0" itemId="0" count="0" isBind="0" appearType="0" validDate="0" isShow="0"/>
	<SevenYearRewardDropInfo id="0" dropId="0" site="494" para2="0" itemId="0" count="0" isBind="0" appearType="0" validDate="0" isShow="0"/>
	<SevenYearRewardDropInfo id="0" dropId="0" site="366" para2="0" itemId="0" count="0" isBind="0" appearType="0" validDate="0" isShow="0"/>
	<SevenYearRewardDropInfo id="0" dropId="0" site="302" para2="0" itemId="0" count="0" isBind="0" appearType="0" validDate="0" isShow="0"/>
	<SevenYearRewardDropInfo id="0" dropId="0" site="238" para2="0" itemId="0" count="0" isBind="0" appearType="0" validDate="0" isShow="0"/>
	<SevenYearRewardDropInfo id="0" dropId="0" site="174" para2="0" itemId="0" count="0" isBind="0" appearType="0" validDate="0" isShow="0"/>
	<SevenYearRewardDropInfo id="0" dropId="0" site="462" para2="0" itemId="0" count="0" isBind="0" appearType="0" validDate="0" isShow="0"/>
	<SevenYearRewardDropInfo id="0" dropId="0" site="398" para2="0" itemId="0" count="0" isBind="0" appearType="0" validDate="0" isShow="0"/>
	<SevenYearRewardDropInfo id="0" dropId="0" site="248" para2="0" itemId="0" count="0" isBind="0" appearType="0" validDate="0" isShow="0"/>
	<SevenYearRewardDropInfo id="0" dropId="0" site="184" para2="0" itemId="0" count="0" isBind="0" appearType="0" validDate="0" isShow="0"/>
	<SevenYearRewardDropInfo id="0" dropId="0" site="472" para2="0" itemId="0" count="0" isBind="0" appearType="0" validDate="0" isShow="0"/>
	<SevenYearRewardDropInfo id="0" dropId="0" site="408" para2="0" itemId="0" count="0" isBind="0" appearType="0" validDate="0" isShow="0"/>
	<SevenYearRewardDropInfo id="0" dropId="0" site="344" para2="0" itemId="0" count="0" isBind="0" appearType="0" validDate="0" isShow="0"/>
	<SevenYearRewardDropInfo id="0" dropId="0" site="216" para2="0" itemId="0" count="0" isBind="0" appearType="0" validDate="0" isShow="0"/>
	<SevenYearRewardDropInfo id="0" dropId="0" site="152" para2="0" itemId="0" count="0" isBind="0" appearType="0" validDate="0" isShow="0"/>
	<SevenYearRewardDropInfo id="0" dropId="0" site="376" para2="0" itemId="0" count="0" isBind="0" appearType="0" validDate="0" isShow="0"/>
	<SevenYearRewardDropInfo id="0" dropId="0" site="312" para2="0" itemId="0" count="0" isBind="0" appearType="0" validDate="0" isShow="0"/>
	<SevenYearRewardDropInfo id="0" dropId="0" site="141" para2="0" itemId="0" count="0" isBind="0" appearType="0" validDate="0" isShow="0"/>
	<SevenYearRewardDropInfo id="0" dropId="0" site="493" para2="0" itemId="0" count="0" isBind="0" appearType="0" validDate="0" isShow="0"/>
	<SevenYearRewardDropInfo id="0" dropId="0" site="429" para2="0" itemId="0" count="0" isBind="0" appearType="0" validDate="0" isShow="0"/>
	<SevenYearRewardDropInfo id="0" dropId="0" site="301" para2="0" itemId="0" count="0" isBind="0" appearType="0" validDate="0" isShow="0"/>
	<SevenYearRewardDropInfo id="0" dropId="0" site="237" para2="0" itemId="0" count="0" isBind="0" appearType="0" validDate="0" isShow="0"/>
	<SevenYearRewardDropInfo id="0" dropId="0" site="173" para2="0" itemId="0" count="0" isBind="0" appearType="0" validDate="0" isShow="0"/>
	<SevenYearRewardDropInfo id="0" dropId="0" site="461" para2="0" itemId="0" count="0" isBind="0" appearType="0" validDate="0" isShow="0"/>
	<SevenYearRewardDropInfo id="0" dropId="0" site="397" para2="0" itemId="0" count="0" isBind="0" appearType="0" validDate="0" isShow="0"/>
	<SevenYearRewardDropInfo id="0" dropId="0" site="333" para2="0" itemId="0" count="0" isBind="0" appearType="0" validDate="0" isShow="0"/>
	<SevenYearRewardDropInfo id="0" dropId="0" site="269" para2="0" itemId="0" count="0" isBind="0" appearType="0" validDate="0" isShow="0"/>
	<SevenYearRewardDropInfo id="0" dropId="0" site="162" para2="0" itemId="0" count="0" isBind="0" appearType="0" validDate="0" isShow="0"/>
	<SevenYearRewardDropInfo id="0" dropId="0" site="386" para2="0" itemId="0" count="0" isBind="0" appearType="0" validDate="0" isShow="0"/>
	<SevenYearRewardDropInfo id="0" dropId="0" site="322" para2="0" itemId="0" count="0" isBind="0" appearType="0" validDate="0" isShow="0"/>
	<SevenYearRewardDropInfo id="0" dropId="0" site="258" para2="0" itemId="0" count="0" isBind="0" appearType="0" validDate="0" isShow="0"/>
	<SevenYearRewardDropInfo id="0" dropId="0" site="194" para2="0" itemId="0" count="0" isBind="0" appearType="0" validDate="0" isShow="0"/>
	<SevenYearRewardDropInfo id="0" dropId="0" site="482" para2="0" itemId="0" count="0" isBind="0" appearType="0" validDate="0" isShow="0"/>
	<SevenYearRewardDropInfo id="0" dropId="0" site="418" para2="0" itemId="0" count="0" isBind="0" appearType="0" validDate="0" isShow="0"/>
	<SevenYearRewardDropInfo id="0" dropId="0" site="354" para2="0" itemId="0" count="0" isBind="0" appearType="0" validDate="0" isShow="0"/>
	<SevenYearRewardDropInfo id="0" dropId="0" site="226" para2="0" itemId="0" count="0" isBind="0" appearType="0" validDate="0" isShow="0"/>
	<SevenYearRewardDropInfo id="0" dropId="0" site="492" para2="0" itemId="0" count="0" isBind="0" appearType="0" validDate="0" isShow="0"/>
	<SevenYearRewardDropInfo id="0" dropId="0" site="428" para2="0" itemId="0" count="0" isBind="0" appearType="0" validDate="0" isShow="0"/>
	<SevenYearRewardDropInfo id="0" dropId="0" site="364" para2="0" itemId="0" count="0" isBind="0" appearType="0" validDate="0" isShow="0"/>
	<SevenYearRewardDropInfo id="0" dropId="0" site="236" para2="0" itemId="0" count="0" isBind="0" appearType="0" validDate="0" isShow="0"/>
	<SevenYearRewardDropInfo id="0" dropId="0" site="172" para2="0" itemId="0" count="0" isBind="0" appearType="0" validDate="0" isShow="0"/>
	<SevenYearRewardDropInfo id="0" dropId="0" site="396" para2="0" itemId="0" count="0" isBind="0" appearType="0" validDate="0" isShow="0"/>
	<SevenYearRewardDropInfo id="0" dropId="0" site="332" para2="0" itemId="0" count="0" isBind="0" appearType="0" validDate="0" isShow="0"/>
	<SevenYearRewardDropInfo id="0" dropId="0" site="268" para2="0" itemId="0" count="0" isBind="0" appearType="0" validDate="0" isShow="0"/>
	<SevenYearRewardDropInfo id="0" dropId="0" site="204" para2="0" itemId="0" count="0" isBind="0" appearType="0" validDate="0" isShow="0"/>
	<SevenYearRewardDropInfo id="0" dropId="0" site="449" para2="0" itemId="0" count="0" isBind="0" appearType="0" validDate="0" isShow="0"/>
	<SevenYearRewardDropInfo id="0" dropId="0" site="321" para2="0" itemId="0" count="0" isBind="0" appearType="0" validDate="0" isShow="0"/>
	<SevenYearRewardDropInfo id="0" dropId="0" site="257" para2="0" itemId="0" count="0" isBind="0" appearType="0" validDate="0" isShow="0"/>
	<SevenYearRewardDropInfo id="0" dropId="0" site="193" para2="0" itemId="0" count="0" isBind="0" appearType="0" validDate="0" isShow="0"/>
	<SevenYearRewardDropInfo id="0" dropId="0" site="129" para2="0" itemId="0" count="0" isBind="0" appearType="0" validDate="0" isShow="0"/>
	<SevenYearRewardDropInfo id="0" dropId="0" site="481" para2="0" itemId="0" count="0" isBind="0" appearType="0" validDate="0" isShow="0"/>
	<SevenYearRewardDropInfo id="0" dropId="0" site="417" para2="0" itemId="0" count="0" isBind="0" appearType="0" validDate="0" isShow="0"/>
	<SevenYearRewardDropInfo id="0" dropId="0" site="353" para2="0" itemId="0" count="0" isBind="0" appearType="0" validDate="0" isShow="0"/>
	<SevenYearRewardDropInfo id="0" dropId="0" site="289" para2="0" itemId="0" count="0" isBind="0" appearType="0" validDate="0" isShow="0"/>
	<SevenYearRewardDropInfo id="0" dropId="0" site="161" para2="0" itemId="0" count="0" isBind="0" appearType="0" validDate="0" isShow="0"/>
	<SevenYearRewardDropInfo id="0" dropId="0" site="406" para2="0" itemId="0" count="0" isBind="0" appearType="0" validDate="0" isShow="0"/>
	<SevenYearRewardDropInfo id="0" dropId="0" site="342" para2="0" itemId="0" count="0" isBind="0" appearType="0" validDate="0" isShow="0"/>
	<SevenYearRewardDropInfo id="0" dropId="0" site="278" para2="0" itemId="0" count="0" isBind="0" appearType="0" validDate="0" isShow="0"/>
	<SevenYearRewardDropInfo id="0" dropId="0" site="214" para2="0" itemId="0" count="0" isBind="0" appearType="0" validDate="0" isShow="0"/>
	<SevenYearRewardDropInfo id="0" dropId="0" site="438" para2="0" itemId="0" count="0" isBind="0" appearType="0" validDate="0" isShow="0"/>
	<SevenYearRewardDropInfo id="0" dropId="0" site="374" para2="0" itemId="0" count="0" isBind="0" appearType="0" validDate="0" isShow="0"/>
	<SevenYearRewardDropInfo id="0" dropId="0" site="246" para2="0" itemId="0" count="0" isBind="0" appearType="0" validDate="0" isShow="0"/>
	<SevenYearRewardDropInfo id="0" dropId="0" site="182" para2="0" itemId="0" count="0" isBind="0" appearType="0" validDate="0" isShow="0"/>
	<SevenYearRewardDropInfo id="0" dropId="0" site="448" para2="0" itemId="0" count="0" isBind="0" appearType="0" validDate="0" isShow="0"/>
	<SevenYearRewardDropInfo id="0" dropId="0" site="384" para2="0" itemId="0" count="0" isBind="0" appearType="0" validDate="0" isShow="0"/>
	<SevenYearRewardDropInfo id="0" dropId="0" site="256" para2="0" itemId="0" count="0" isBind="0" appearType="0" validDate="0" isShow="0"/>
	<SevenYearRewardDropInfo id="0" dropId="0" site="192" para2="0" itemId="0" count="0" isBind="0" appearType="0" validDate="0" isShow="0"/>
	<SevenYearRewardDropInfo id="0" dropId="0" site="128" para2="0" itemId="0" count="0" isBind="0" appearType="0" validDate="0" isShow="0"/>
	<SevenYearRewardDropInfo id="0" dropId="0" site="416" para2="0" itemId="0" count="0" isBind="0" appearType="0" validDate="0" isShow="0"/>
	<SevenYearRewardDropInfo id="0" dropId="0" site="352" para2="0" itemId="0" count="0" isBind="0" appearType="0" validDate="0" isShow="0"/>
	<SevenYearRewardDropInfo id="0" dropId="0" site="288" para2="0" itemId="0" count="0" isBind="0" appearType="0" validDate="0" isShow="0"/>
	<SevenYearRewardDropInfo id="0" dropId="0" site="224" para2="0" itemId="0" count="0" isBind="0" appearType="0" validDate="0" isShow="0"/>
	<SevenYearRewardDropInfo id="0" dropId="0" site="98" para2="0" itemId="0" count="0" isBind="0" appearType="0" validDate="0" isShow="0"/>
	<SevenYearRewardDropInfo id="0" dropId="0" site="469" para2="0" itemId="0" count="0" isBind="0" appearType="0" validDate="0" isShow="0"/>
	<SevenYearRewardDropInfo id="0" dropId="0" site="341" para2="0" itemId="0" count="0" isBind="0" appearType="0" validDate="0" isShow="0"/>
	<SevenYearRewardDropInfo id="0" dropId="0" site="277" para2="0" itemId="0" count="0" isBind="0" appearType="0" validDate="0" isShow="0"/>
	<SevenYearRewardDropInfo id="0" dropId="0" site="213" para2="0" itemId="0" count="0" isBind="0" appearType="0" validDate="0" isShow="0"/>
	<SevenYearRewardDropInfo id="0" dropId="0" site="149" para2="0" itemId="0" count="0" isBind="0" appearType="0" validDate="0" isShow="0"/>
	<SevenYearRewardDropInfo id="0" dropId="0" site="88" para2="0" itemId="0" count="0" isBind="0" appearType="0" validDate="0" isShow="0"/>
	<SevenYearRewardDropInfo id="0" dropId="0" site="437" para2="0" itemId="0" count="0" isBind="0" appearType="0" validDate="0" isShow="0"/>
	<SevenYearRewardDropInfo id="0" dropId="0" site="373" para2="0" itemId="0" count="0" isBind="0" appearType="0" validDate="0" isShow="0"/>
	<SevenYearRewardDropInfo id="0" dropId="0" site="309" para2="0" itemId="0" count="0" isBind="0" appearType="0" validDate="0" isShow="0"/>
	<SevenYearRewardDropInfo id="0" dropId="0" site="181" para2="0" itemId="0" count="0" isBind="0" appearType="0" validDate="0" isShow="0"/>
	<SevenYearRewardDropInfo id="0" dropId="0" site="118" para2="0" itemId="0" count="0" isBind="0" appearType="0" validDate="0" isShow="0"/>
	<SevenYearRewardDropInfo id="0" dropId="0" site="426" para2="0" itemId="0" count="0" isBind="0" appearType="0" validDate="0" isShow="0"/>
	<SevenYearRewardDropInfo id="0" dropId="0" site="362" para2="0" itemId="0" count="0" isBind="0" appearType="0" validDate="0" isShow="0"/>
	<SevenYearRewardDropInfo id="0" dropId="0" site="298" para2="0" itemId="0" count="0" isBind="0" appearType="0" validDate="0" isShow="0"/>
	<SevenYearRewardDropInfo id="0" dropId="0" site="234" para2="0" itemId="0" count="0" isBind="0" appearType="0" validDate="0" isShow="0"/>
	<SevenYearRewardDropInfo id="0" dropId="0" site="108" para2="0" itemId="0" count="0" isBind="0" appearType="0" validDate="0" isShow="0"/>
	<SevenYearRewardDropInfo id="0" dropId="0" site="458" para2="0" itemId="0" count="0" isBind="0" appearType="0" validDate="0" isShow="0"/>
	<SevenYearRewardDropInfo id="0" dropId="0" site="394" para2="0" itemId="0" count="0" isBind="0" appearType="0" validDate="0" isShow="0"/>
	<SevenYearRewardDropInfo id="0" dropId="0" site="266" para2="0" itemId="0" count="0" isBind="0" appearType="0" validDate="0" isShow="0"/>
	<SevenYearRewardDropInfo id="0" dropId="0" site="202" para2="0" itemId="0" count="0" isBind="0" appearType="0" validDate="0" isShow="0"/>
	<SevenYearRewardDropInfo id="0" dropId="0" site="138" para2="0" itemId="0" count="0" isBind="0" appearType="0" validDate="0" isShow="0"/>
	<SevenYearRewardDropInfo id="0" dropId="0" site="468" para2="0" itemId="0" count="0" isBind="0" appearType="0" validDate="0" isShow="0"/>
	<SevenYearRewardDropInfo id="0" dropId="0" site="404" para2="0" itemId="0" count="0" isBind="0" appearType="0" validDate="0" isShow="0"/>
	<SevenYearRewardDropInfo id="0" dropId="0" site="276" para2="0" itemId="0" count="0" isBind="0" appearType="0" validDate="0" isShow="0"/>
	<SevenYearRewardDropInfo id="0" dropId="0" site="212" para2="0" itemId="0" count="0" isBind="0" appearType="0" validDate="0" isShow="0"/>
	<SevenYearRewardDropInfo id="0" dropId="0" site="148" para2="0" itemId="0" count="0" isBind="0" appearType="0" validDate="0" isShow="0"/>
	<SevenYearRewardDropInfo id="0" dropId="0" site="436" para2="0" itemId="0" count="0" isBind="0" appearType="0" validDate="0" isShow="0"/>
	<SevenYearRewardDropInfo id="0" dropId="0" site="372" para2="0" itemId="0" count="0" isBind="0" appearType="0" validDate="0" isShow="0"/>
	<SevenYearRewardDropInfo id="0" dropId="0" site="308" para2="0" itemId="0" count="0" isBind="0" appearType="0" validDate="0" isShow="0"/>
	<SevenYearRewardDropInfo id="0" dropId="0" site="244" para2="0" itemId="0" count="0" isBind="0" appearType="0" validDate="0" isShow="0"/>
	<SevenYearRewardDropInfo id="0" dropId="0" site="117" para2="0" itemId="0" count="0" isBind="0" appearType="0" validDate="0" isShow="0"/>
	<SevenYearRewardDropInfo id="0" dropId="0" site="489" para2="0" itemId="0" count="0" isBind="0" appearType="0" validDate="0" isShow="0"/>
	<SevenYearRewardDropInfo id="0" dropId="0" site="361" para2="0" itemId="0" count="0" isBind="0" appearType="0" validDate="0" isShow="0"/>
	<SevenYearRewardDropInfo id="0" dropId="0" site="297" para2="0" itemId="0" count="0" isBind="0" appearType="0" validDate="0" isShow="0"/>
	<SevenYearRewardDropInfo id="0" dropId="0" site="233" para2="0" itemId="0" count="0" isBind="0" appearType="0" validDate="0" isShow="0"/>
	<SevenYearRewardDropInfo id="0" dropId="0" site="169" para2="0" itemId="0" count="0" isBind="0" appearType="0" validDate="0" isShow="0"/>
	<SevenYearRewardDropInfo id="0" dropId="0" site="457" para2="0" itemId="0" count="0" isBind="0" appearType="0" validDate="0" isShow="0"/>
	<SevenYearRewardDropInfo id="0" dropId="0" site="393" para2="0" itemId="0" count="0" isBind="0" appearType="0" validDate="0" isShow="0"/>
	<SevenYearRewardDropInfo id="0" dropId="0" site="329" para2="0" itemId="0" count="0" isBind="0" appearType="0" validDate="0" isShow="0"/>
	<SevenYearRewardDropInfo id="0" dropId="0" site="201" para2="0" itemId="0" count="0" isBind="0" appearType="0" validDate="0" isShow="0"/>
	<SevenYearRewardDropInfo id="0" dropId="0" site="137" para2="0" itemId="0" count="0" isBind="0" appearType="0" validDate="0" isShow="0"/>
	<SevenYearRewardDropInfo id="0" dropId="0" site="446" para2="0" itemId="0" count="0" isBind="0" appearType="0" validDate="0" isShow="0"/>
	<SevenYearRewardDropInfo id="0" dropId="0" site="382" para2="0" itemId="0" count="0" isBind="0" appearType="0" validDate="0" isShow="0"/>
	<SevenYearRewardDropInfo id="0" dropId="0" site="318" para2="0" itemId="0" count="0" isBind="0" appearType="0" validDate="0" isShow="0"/>
	<SevenYearRewardDropInfo id="0" dropId="0" site="254" para2="0" itemId="0" count="0" isBind="0" appearType="0" validDate="0" isShow="0"/>
	<SevenYearRewardDropInfo id="0" dropId="0" site="126" para2="0" itemId="0" count="0" isBind="0" appearType="0" validDate="0" isShow="0"/>
	<SevenYearRewardDropInfo id="0" dropId="0" site="478" para2="0" itemId="0" count="0" isBind="0" appearType="0" validDate="0" isShow="0"/>
	<SevenYearRewardDropInfo id="0" dropId="0" site="414" para2="0" itemId="0" count="0" isBind="0" appearType="0" validDate="0" isShow="0"/>
	<SevenYearRewardDropInfo id="0" dropId="0" site="286" para2="0" itemId="0" count="0" isBind="0" appearType="0" validDate="0" isShow="0"/>
	<SevenYearRewardDropInfo id="0" dropId="0" site="222" para2="0" itemId="0" count="0" isBind="0" appearType="0" validDate="0" isShow="0"/>
	<SevenYearRewardDropInfo id="0" dropId="0" site="158" para2="0" itemId="0" count="0" isBind="0" appearType="0" validDate="0" isShow="0"/>
	<SevenYearRewardDropInfo id="0" dropId="0" site="96" para2="0" itemId="0" count="0" isBind="0" appearType="0" validDate="0" isShow="0"/>
	<SevenYearRewardDropInfo id="19100101" dropId="191001" site="1" para2="0" itemId="1098110" count="1" isBind="1" appearType="1" validDate="0" isShow="0"/>
	<SevenYearRewardDropInfo id="19100104" dropId="191001" site="1" para2="0" itemId="1128110" count="1" isBind="1" appearType="1" validDate="0" isShow="0"/>
	<SevenYearRewardDropInfo id="19100103" dropId="191001" site="1" para2="0" itemId="1118110" count="1" isBind="1" appearType="1" validDate="0" isShow="0"/>
	<SevenYearRewardDropInfo id="19100102" dropId="191001" site="1" para2="0" itemId="1108110" count="1" isBind="1" appearType="1" validDate="0" isShow="0"/>
	<SevenYearRewardDropInfo id="19100201" dropId="191002" site="2" para2="0" itemId="1118080" count="1" isBind="1" appearType="1" validDate="0" isShow="0"/>
	<SevenYearRewardDropInfo id="19100301" dropId="191003" site="3" para2="0" itemId="2180866" count="1" isBind="1" appearType="1" validDate="0" isShow="0"/>
	<SevenYearRewardDropInfo id="19100401" dropId="191004" site="4" para2="0" itemId="3061001" count="1" isBind="1" appearType="1" validDate="0" isShow="0"/>
	<SevenYearRewardDropInfo id="19100501" dropId="191005" site="5" para2="1" itemId="1108163" count="1" isBind="1" appearType="1" validDate="0" isShow="0"/>
	<SevenYearRewardDropInfo id="19100601" dropId="191006" site="6" para2="0" itemId="212029" count="15" isBind="1" appearType="1" validDate="0" isShow="0"/>
	<SevenYearRewardDropInfo id="19100701" dropId="191007" site="7" para2="0" itemId="208550" count="10" isBind="1" appearType="1" validDate="0" isShow="0"/>
	<SevenYearRewardDropInfo id="19100801" dropId="191008" site="8" para2="0" itemId="212028" count="50" isBind="1" appearType="1" validDate="0" isShow="0"/>
	<SevenYearRewardDropInfo id="19100901" dropId="191009" site="9" para2="0" itemId="208500" count="5" isBind="1" appearType="1" validDate="0" isShow="0"/>
	<SevenYearRewardDropInfo id="19101002" dropId="191010" site="10" para2="1" itemId="6920001" count="20" isBind="1" appearType="1" validDate="0" isShow="0"/>
	<SevenYearRewardDropInfo id="19101001" dropId="191010" site="10" para2="1" itemId="6930001" count="1" isBind="1" appearType="1" validDate="0" isShow="0"/>
	<SevenYearRewardDropInfo id="19101101" dropId="191011" site="11" para2="0" itemId="212030" count="15" isBind="1" appearType="1" validDate="0" isShow="0"/>
	<SevenYearRewardDropInfo id="19101201" dropId="191012" site="12" para2="0" itemId="208550" count="10" isBind="1" appearType="1" validDate="0" isShow="0"/>
	<SevenYearRewardDropInfo id="19101301" dropId="191013" site="13" para2="0" itemId="212028" count="50" isBind="1" appearType="1" validDate="0" isShow="0"/>
	<SevenYearRewardDropInfo id="19101401" dropId="191014" site="14" para2="0" itemId="208500" count="5" isBind="1" appearType="1" validDate="0" isShow="0"/>
	<SevenYearRewardDropInfo id="19101501" dropId="191015" site="15" para2="1" itemId="208510" count="100" isBind="1" appearType="1" validDate="0" isShow="0"/>
	<SevenYearRewardDropInfo id="19101601" dropId="191016" site="16" para2="0" itemId="212031" count="15" isBind="1" appearType="1" validDate="0" isShow="0"/>
	<SevenYearRewardDropInfo id="19101701" dropId="191017" site="17" para2="0" itemId="208550" count="10" isBind="1" appearType="1" validDate="0" isShow="0"/>
	<SevenYearRewardDropInfo id="19101801" dropId="191018" site="18" para2="0" itemId="212028" count="50" isBind="1" appearType="1" validDate="0" isShow="0"/>
	<SevenYearRewardDropInfo id="19101901" dropId="191019" site="19" para2="0" itemId="208500" count="10" isBind="1" appearType="1" validDate="0" isShow="0"/>
	<SevenYearRewardDropInfo id="19102002" dropId="191020" site="20" para2="1" itemId="6920001" count="20" isBind="1" appearType="1" validDate="0" isShow="0"/>
	<SevenYearRewardDropInfo id="19102001" dropId="191020" site="20" para2="1" itemId="6930001" count="1" isBind="1" appearType="1" validDate="0" isShow="0"/>
	<SevenYearRewardDropInfo id="19102101" dropId="191021" site="21" para2="0" itemId="212032" count="15" isBind="1" appearType="1" validDate="0" isShow="0"/>
	<SevenYearRewardDropInfo id="19102201" dropId="191022" site="22" para2="0" itemId="208550" count="10" isBind="1" appearType="1" validDate="0" isShow="0"/>
	<SevenYearRewardDropInfo id="19102301" dropId="191023" site="23" para2="0" itemId="212028" count="50" isBind="1" appearType="1" validDate="0" isShow="0"/>
	<SevenYearRewardDropInfo id="19102401" dropId="191024" site="24" para2="0" itemId="208500" count="10" isBind="1" appearType="1" validDate="0" isShow="0"/>
	<SevenYearRewardDropInfo id="19102501" dropId="191025" site="25" para2="1" itemId="208500" count="50" isBind="1" appearType="1" validDate="0" isShow="0"/>
	<SevenYearRewardDropInfo id="19102601" dropId="191026" site="26" para2="0" itemId="212033" count="15" isBind="1" appearType="1" validDate="0" isShow="0"/>
	<SevenYearRewardDropInfo id="19102701" dropId="191027" site="27" para2="0" itemId="208550" count="20" isBind="1" appearType="1" validDate="0" isShow="0"/>
	<SevenYearRewardDropInfo id="19102801" dropId="191028" site="28" para2="0" itemId="212028" count="50" isBind="1" appearType="1" validDate="0" isShow="0"/>
	<SevenYearRewardDropInfo id="19102901" dropId="191029" site="29" para2="0" itemId="208500" count="10" isBind="1" appearType="1" validDate="0" isShow="0"/>
	<SevenYearRewardDropInfo id="19103002" dropId="191030" site="30" para2="1" itemId="6920001" count="20" isBind="1" appearType="1" validDate="0" isShow="0"/>
	<SevenYearRewardDropInfo id="19103001" dropId="191030" site="30" para2="1" itemId="6930001" count="1" isBind="1" appearType="1" validDate="0" isShow="0"/>
	<SevenYearRewardDropInfo id="19103101" dropId="191031" site="31" para2="0" itemId="6260003" count="5" isBind="1" appearType="1" validDate="0" isShow="0"/>
	<SevenYearRewardDropInfo id="19103201" dropId="191032" site="32" para2="0" itemId="208550" count="20" isBind="1" appearType="1" validDate="0" isShow="0"/>
	<SevenYearRewardDropInfo id="19103301" dropId="191033" site="33" para2="0" itemId="212028" count="50" isBind="1" appearType="1" validDate="0" isShow="0"/>
	<SevenYearRewardDropInfo id="19103401" dropId="191034" site="34" para2="0" itemId="208500" count="20" isBind="1" appearType="1" validDate="0" isShow="0"/>
	<SevenYearRewardDropInfo id="19103501" dropId="191035" site="35" para2="1" itemId="212034" count="10" isBind="1" appearType="1" validDate="0" isShow="0"/>
	<SevenYearRewardDropInfo id="19103601" dropId="191036" site="36" para2="0" itemId="6260003" count="10" isBind="1" appearType="1" validDate="0" isShow="0"/>
	<SevenYearRewardDropInfo id="19103701" dropId="191037" site="37" para2="0" itemId="208550" count="20" isBind="1" appearType="1" validDate="0" isShow="0"/>
	<SevenYearRewardDropInfo id="19103801" dropId="191038" site="38" para2="0" itemId="212028" count="50" isBind="1" appearType="1" validDate="0" isShow="0"/>
	<SevenYearRewardDropInfo id="19103901" dropId="191039" site="39" para2="0" itemId="208500" count="20" isBind="1" appearType="1" validDate="0" isShow="0"/>
	<SevenYearRewardDropInfo id="19104002" dropId="191040" site="40" para2="1" itemId="6920001" count="20" isBind="1" appearType="1" validDate="0" isShow="0"/>
	<SevenYearRewardDropInfo id="19104001" dropId="191040" site="40" para2="1" itemId="6930001" count="1" isBind="1" appearType="1" validDate="0" isShow="0"/>
	<SevenYearRewardDropInfo id="19104101" dropId="191041" site="41" para2="0" itemId="2183046" count="1" isBind="1" appearType="1" validDate="0" isShow="0"/>
	<SevenYearRewardDropInfo id="19104201" dropId="191042" site="42" para2="0" itemId="208550" count="20" isBind="1" appearType="1" validDate="0" isShow="0"/>
	<SevenYearRewardDropInfo id="19104301" dropId="191043" site="43" para2="0" itemId="212028" count="100" isBind="1" appearType="1" validDate="0" isShow="0"/>
	<SevenYearRewardDropInfo id="19104401" dropId="191044" site="44" para2="0" itemId="208500" count="20" isBind="1" appearType="1" validDate="0" isShow="0"/>
	<SevenYearRewardDropInfo id="19104501" dropId="191045" site="45" para2="1" itemId="6260003" count="10" isBind="1" appearType="1" validDate="0" isShow="0"/>
	<SevenYearRewardDropInfo id="19104601" dropId="191046" site="46" para2="0" itemId="212029" count="30" isBind="1" appearType="1" validDate="0" isShow="0"/>
	<SevenYearRewardDropInfo id="19104701" dropId="191047" site="47" para2="0" itemId="208550" count="20" isBind="1" appearType="1" validDate="0" isShow="0"/>
	<SevenYearRewardDropInfo id="19104801" dropId="191048" site="48" para2="0" itemId="212028" count="100" isBind="1" appearType="1" validDate="0" isShow="0"/>
	<SevenYearRewardDropInfo id="19104901" dropId="191049" site="49" para2="0" itemId="208500" count="30" isBind="1" appearType="1" validDate="0" isShow="0"/>
	<SevenYearRewardDropInfo id="19105002" dropId="191050" site="50" para2="1" itemId="6920001" count="20" isBind="1" appearType="1" validDate="0" isShow="0"/>
	<SevenYearRewardDropInfo id="19105001" dropId="191050" site="50" para2="1" itemId="6930001" count="1" isBind="1" appearType="1" validDate="0" isShow="0"/>
	<SevenYearRewardDropInfo id="19105101" dropId="191051" site="51" para2="0" itemId="212030" count="30" isBind="1" appearType="1" validDate="0" isShow="0"/>
	<SevenYearRewardDropInfo id="19105201" dropId="191052" site="52" para2="0" itemId="208550" count="30" isBind="1" appearType="1" validDate="0" isShow="0"/>
	<SevenYearRewardDropInfo id="19105301" dropId="191053" site="53" para2="0" itemId="212028" count="100" isBind="1" appearType="1" validDate="0" isShow="0"/>
	<SevenYearRewardDropInfo id="19105401" dropId="191054" site="54" para2="0" itemId="208500" count="30" isBind="1" appearType="1" validDate="0" isShow="0"/>
	<SevenYearRewardDropInfo id="19105501" dropId="191055" site="55" para2="1" itemId="1118163" count="1" isBind="1" appearType="1" validDate="0" isShow="0"/>
	<SevenYearRewardDropInfo id="19105601" dropId="191056" site="56" para2="0" itemId="212031" count="30" isBind="1" appearType="1" validDate="0" isShow="0"/>
	<SevenYearRewardDropInfo id="19105701" dropId="191057" site="57" para2="0" itemId="208550" count="30" isBind="1" appearType="1" validDate="0" isShow="0"/>
	<SevenYearRewardDropInfo id="19105801" dropId="191058" site="58" para2="0" itemId="212028" count="100" isBind="1" appearType="1" validDate="0" isShow="0"/>
	<SevenYearRewardDropInfo id="19105901" dropId="191059" site="59" para2="0" itemId="208500" count="30" isBind="1" appearType="1" validDate="0" isShow="0"/>
	<SevenYearRewardDropInfo id="19106002" dropId="191060" site="60" para2="1" itemId="6920001" count="20" isBind="1" appearType="1" validDate="0" isShow="0"/>
	<SevenYearRewardDropInfo id="19106001" dropId="191060" site="60" para2="1" itemId="6930001" count="1" isBind="1" appearType="1" validDate="0" isShow="0"/>
	<SevenYearRewardDropInfo id="19106101" dropId="191061" site="61" para2="0" itemId="212032" count="30" isBind="1" appearType="1" validDate="0" isShow="0"/>
	<SevenYearRewardDropInfo id="19106201" dropId="191062" site="62" para2="0" itemId="208550" count="30" isBind="1" appearType="1" validDate="0" isShow="0"/>
	<SevenYearRewardDropInfo id="19106301" dropId="191063" site="63" para2="0" itemId="212028" count="100" isBind="1" appearType="1" validDate="0" isShow="0"/>
	<SevenYearRewardDropInfo id="19106401" dropId="191064" site="64" para2="0" itemId="208500" count="40" isBind="1" appearType="1" validDate="0" isShow="0"/>
	<SevenYearRewardDropInfo id="19106501" dropId="191065" site="65" para2="1" itemId="208500" count="50" isBind="1" appearType="1" validDate="0" isShow="0"/>
	<SevenYearRewardDropInfo id="19106601" dropId="191066" site="66" para2="0" itemId="212033" count="30" isBind="1" appearType="1" validDate="0" isShow="0"/>
	<SevenYearRewardDropInfo id="19106701" dropId="191067" site="67" para2="0" itemId="208550" count="30" isBind="1" appearType="1" validDate="0" isShow="0"/>
	<SevenYearRewardDropInfo id="19106801" dropId="191068" site="68" para2="0" itemId="212028" count="100" isBind="1" appearType="1" validDate="0" isShow="0"/>
	<SevenYearRewardDropInfo id="19106901" dropId="191069" site="69" para2="0" itemId="208500" count="40" isBind="1" appearType="1" validDate="0" isShow="0"/>
	<SevenYearRewardDropInfo id="19107002" dropId="191070" site="70" para2="1" itemId="6920001" count="20" isBind="1" appearType="1" validDate="0" isShow="0"/>
	<SevenYearRewardDropInfo id="19107001" dropId="191070" site="70" para2="1" itemId="6930001" count="1" isBind="1" appearType="1" validDate="0" isShow="0"/>
	<SevenYearRewardDropInfo id="19107101" dropId="191071" site="71" para2="0" itemId="6260003" count="20" isBind="1" appearType="1" validDate="0" isShow="0"/>
	<SevenYearRewardDropInfo id="19107201" dropId="191072" site="72" para2="0" itemId="208550" count="30" isBind="1" appearType="1" validDate="0" isShow="0"/>
	<SevenYearRewardDropInfo id="19107301" dropId="191073" site="73" para2="0" itemId="212028" count="100" isBind="1" appearType="1" validDate="0" isShow="0"/>
	<SevenYearRewardDropInfo id="19107401" dropId="191074" site="74" para2="0" itemId="208500" count="40" isBind="1" appearType="1" validDate="0" isShow="0"/>
	<SevenYearRewardDropInfo id="19107501" dropId="191075" site="75" para2="1" itemId="6260002" count="15" isBind="1" appearType="1" validDate="0" isShow="0"/>
	<SevenYearRewardDropInfo id="19107601" dropId="191076" site="76" para2="0" itemId="6260003" count="30" isBind="1" appearType="1" validDate="0" isShow="0"/>
	<SevenYearRewardDropInfo id="19107701" dropId="191077" site="77" para2="0" itemId="208550" count="50" isBind="1" appearType="1" validDate="0" isShow="0"/>
	<SevenYearRewardDropInfo id="19107801" dropId="191078" site="78" para2="0" itemId="212028" count="100" isBind="1" appearType="1" validDate="0" isShow="0"/>
	<SevenYearRewardDropInfo id="19107901" dropId="191079" site="79" para2="0" itemId="208500" count="80" isBind="1" appearType="1" validDate="0" isShow="0"/>
	<SevenYearRewardDropInfo id="19108002" dropId="191080" site="80" para2="1" itemId="6920001" count="20" isBind="1" appearType="1" validDate="0" isShow="0"/>
	<SevenYearRewardDropInfo id="19108001" dropId="191080" site="80" para2="1" itemId="6930001" count="1" isBind="1" appearType="1" validDate="0" isShow="0"/>
	<SevenYearRewardDropInfo id="19108101" dropId="191081" site="81" para2="0" itemId="2183047" count="1" isBind="1" appearType="1" validDate="0" isShow="0"/>
	<SevenYearRewardDropInfo id="19108301" dropId="191083" site="83" para2="0" itemId="208064" count="40" isBind="1" appearType="1" validDate="0" isShow="0"/>
	<SevenYearRewardDropInfo id="19108501" dropId="191085" site="85" para2="1" itemId="208066" count="30" isBind="1" appearType="1" validDate="0" isShow="0"/>
	<SevenYearRewardDropInfo id="19108701" dropId="191087" site="87" para2="0" itemId="6920001" count="80" isBind="1" appearType="1" validDate="0" isShow="0"/>
	<SevenYearRewardDropInfo id="19108901" dropId="191089" site="89" para2="0" itemId="212030" count="40" isBind="1" appearType="1" validDate="0" isShow="0"/>
	<SevenYearRewardDropInfo id="19109002" dropId="191090" site="90" para2="1" itemId="6920001" count="20" isBind="1" appearType="1" validDate="0" isShow="0"/>
	<SevenYearRewardDropInfo id="19109001" dropId="191090" site="90" para2="1" itemId="6930001" count="1" isBind="1" appearType="1" validDate="0" isShow="0"/>
	<SevenYearRewardDropInfo id="19109101" dropId="191091" site="91" para2="0" itemId="6920001" count="90" isBind="1" appearType="1" validDate="0" isShow="0"/>
	<SevenYearRewardDropInfo id="19109301" dropId="191093" site="93" para2="0" itemId="212031" count="40" isBind="1" appearType="1" validDate="0" isShow="0"/>
	<SevenYearRewardDropInfo id="19109501" dropId="191095" site="95" para2="1" itemId="208067" count="30" isBind="1" appearType="1" validDate="0" isShow="0"/>
	<SevenYearRewardDropInfo id="19109701" dropId="191097" site="97" para2="0" itemId="212032" count="40" isBind="1" appearType="1" validDate="0" isShow="0"/>
	<SevenYearRewardDropInfo id="19109901" dropId="191099" site="99" para2="0" itemId="6670011" count="2" isBind="1" appearType="1" validDate="0" isShow="0"/>
	<SevenYearRewardDropInfo id="19110001" dropId="191100" site="100" para2="1" itemId="1128163" count="1" isBind="1" appearType="1" validDate="0" isShow="0"/>
	<SevenYearRewardDropInfo id="19110101" dropId="191101" site="101" para2="0" itemId="212033" count="40" isBind="1" appearType="1" validDate="0" isShow="0"/>
	<SevenYearRewardDropInfo id="19110301" dropId="191103" site="103" para2="0" itemId="6670012" count="2" isBind="1" appearType="1" validDate="0" isShow="0"/>
	<SevenYearRewardDropInfo id="19110501" dropId="191105" site="105" para2="1" itemId="2120107" count="30" isBind="1" appearType="1" validDate="0" isShow="0"/>
	<SevenYearRewardDropInfo id="19110701" dropId="191107" site="107" para2="0" itemId="6670013" count="2" isBind="1" appearType="1" validDate="0" isShow="0"/>
	<SevenYearRewardDropInfo id="19110901" dropId="191109" site="109" para2="0" itemId="212028" count="200" isBind="1" appearType="1" validDate="0" isShow="0"/>
	<SevenYearRewardDropInfo id="19111002" dropId="191110" site="110" para2="1" itemId="6920001" count="20" isBind="1" appearType="1" validDate="0" isShow="0"/>
	<SevenYearRewardDropInfo id="19111001" dropId="191110" site="110" para2="1" itemId="6930001" count="1" isBind="1" appearType="1" validDate="0" isShow="0"/>
	<SevenYearRewardDropInfo id="19111101" dropId="191111" site="111" para2="0" itemId="6670014" count="2" isBind="1" appearType="1" validDate="0" isShow="0"/>
	<SevenYearRewardDropInfo id="19111501" dropId="191115" site="115" para2="1" itemId="2120106" count="30" isBind="1" appearType="1" validDate="0" isShow="0"/>
	<SevenYearRewardDropInfo id="19111901" dropId="191119" site="119" para2="0" itemId="208064" count="50" isBind="1" appearType="1" validDate="0" isShow="0"/>
	<SevenYearRewardDropInfo id="19112002" dropId="191120" site="120" para2="1" itemId="6920001" count="20" isBind="1" appearType="1" validDate="0" isShow="0"/>
	<SevenYearRewardDropInfo id="19112001" dropId="191120" site="120" para2="1" itemId="6930001" count="1" isBind="1" appearType="1" validDate="0" isShow="0"/>
	<SevenYearRewardDropInfo id="19112301" dropId="191123" site="123" para2="0" itemId="212029" count="50" isBind="1" appearType="1" validDate="0" isShow="0"/>
	<SevenYearRewardDropInfo id="19112501" dropId="191125" site="125" para2="1" itemId="208550" count="50" isBind="1" appearType="1" validDate="0" isShow="0"/>
	<SevenYearRewardDropInfo id="19112701" dropId="191127" site="127" para2="0" itemId="6920001" count="110" isBind="1" appearType="1" validDate="0" isShow="0"/>
	<SevenYearRewardDropInfo id="19113001" dropId="191130" site="130" para2="1" itemId="212034" count="20" isBind="1" appearType="1" validDate="0" isShow="0"/>
	<SevenYearRewardDropInfo id="19113101" dropId="191131" site="131" para2="0" itemId="212030" count="50" isBind="1" appearType="1" validDate="0" isShow="0"/>
	<SevenYearRewardDropInfo id="19113501" dropId="191135" site="135" para2="1" itemId="2120107" count="30" isBind="1" appearType="1" validDate="0" isShow="0"/>
	<SevenYearRewardDropInfo id="19113901" dropId="191139" site="139" para2="0" itemId="212031" count="50" isBind="1" appearType="1" validDate="0" isShow="0"/>
	<SevenYearRewardDropInfo id="19114001" dropId="191140" site="140" para2="1" itemId="2120106" count="30" isBind="1" appearType="1" validDate="0" isShow="0"/>
	<SevenYearRewardDropInfo id="19114301" dropId="191143" site="143" para2="0" itemId="6920001" count="130" isBind="1" appearType="1" validDate="0" isShow="0"/>
	<SevenYearRewardDropInfo id="19114501" dropId="191145" site="145" para2="1" itemId="6260002" count="15" isBind="1" appearType="1" validDate="0" isShow="0"/>
	<SevenYearRewardDropInfo id="19114701" dropId="191147" site="147" para2="0" itemId="212032" count="50" isBind="1" appearType="1" validDate="0" isShow="0"/>
	<SevenYearRewardDropInfo id="19115001" dropId="191150" site="150" para2="1" itemId="1098163" count="1" isBind="1" appearType="1" validDate="0" isShow="0"/>
	<SevenYearRewardDropInfo id="19115101" dropId="191151" site="151" para2="0" itemId="6670011" count="2" isBind="1" appearType="1" validDate="0" isShow="0"/>
	<SevenYearRewardDropInfo id="19115501" dropId="191155" site="155" para2="1" itemId="6260003" count="10" isBind="1" appearType="1" validDate="0" isShow="0"/>
	<SevenYearRewardDropInfo id="19115901" dropId="191159" site="159" para2="0" itemId="6670012" count="2" isBind="1" appearType="1" validDate="0" isShow="0"/>
	<SevenYearRewardDropInfo id="19116001" dropId="191160" site="160" para2="1" itemId="6920001" count="100" isBind="1" appearType="1" validDate="0" isShow="0"/>
	<SevenYearRewardDropInfo id="19116301" dropId="191163" site="163" para2="0" itemId="208550" count="50" isBind="1" appearType="1" validDate="0" isShow="0"/>
	<SevenYearRewardDropInfo id="19116501" dropId="191165" site="165" para2="1" itemId="208062" count="100" isBind="1" appearType="1" validDate="0" isShow="0"/>
	<SevenYearRewardDropInfo id="19116701" dropId="191167" site="167" para2="0" itemId="6670013" count="2" isBind="1" appearType="1" validDate="0" isShow="0"/>
	<SevenYearRewardDropInfo id="19117001" dropId="191170" site="170" para2="1" itemId="208500" count="100" isBind="1" appearType="1" validDate="0" isShow="0"/>
	<SevenYearRewardDropInfo id="19117101" dropId="191171" site="171" para2="0" itemId="212028" count="300" isBind="1" appearType="1" validDate="0" isShow="0"/>
	<SevenYearRewardDropInfo id="19117501" dropId="191175" site="175" para2="1" itemId="21260418" count="2" isBind="1" appearType="1" validDate="0" isShow="0"/>
	<SevenYearRewardDropInfo id="19117901" dropId="191179" site="179" para2="0" itemId="2183052" count="1" isBind="1" appearType="1" validDate="0" isShow="0"/>
	<SevenYearRewardDropInfo id="19118001" dropId="191180" site="180" para2="1" itemId="5010001" count="50" isBind="1" appearType="1" validDate="0" isShow="0"/>
	<SevenYearRewardDropInfo id="19118301" dropId="191183" site="183" para2="0" itemId="208064" count="100" isBind="1" appearType="1" validDate="0" isShow="0"/>
	<SevenYearRewardDropInfo id="19118501" dropId="191185" site="185" para2="1" itemId="21260569" count="1" isBind="1" appearType="1" validDate="0" isShow="0"/>
	<SevenYearRewardDropInfo id="19118701" dropId="191187" site="187" para2="0" itemId="212029" count="60" isBind="1" appearType="1" validDate="0" isShow="0"/>
	<SevenYearRewardDropInfo id="19119001" dropId="191190" site="190" para2="1" itemId="208063" count="100" isBind="1" appearType="1" validDate="0" isShow="0"/>
	<SevenYearRewardDropInfo id="19119101" dropId="191191" site="191" para2="0" itemId="6920001" count="140" isBind="1" appearType="1" validDate="0" isShow="0"/>
	<SevenYearRewardDropInfo id="19119501" dropId="191195" site="195" para2="1" itemId="208500" count="100" isBind="1" appearType="1" validDate="0" isShow="0"/>
	<SevenYearRewardDropInfo id="19119901" dropId="191199" site="199" para2="0" itemId="6920001" count="150" isBind="1" appearType="1" validDate="0" isShow="0"/>
	<SevenYearRewardDropInfo id="19120001" dropId="191200" site="200" para2="1" itemId="1106433" count="1" isBind="1" appearType="1" validDate="0" isShow="0"/>
	<SevenYearRewardDropInfo id="19120301" dropId="191203" site="203" para2="0" itemId="212031" count="60" isBind="1" appearType="1" validDate="0" isShow="0"/>
	<SevenYearRewardDropInfo id="19120501" dropId="191205" site="205" para2="1" itemId="208550" count="50" isBind="1" appearType="1" validDate="0" isShow="0"/>
	<SevenYearRewardDropInfo id="19120701" dropId="191207" site="207" para2="0" itemId="6920001" count="160" isBind="1" appearType="1" validDate="0" isShow="0"/>
	<SevenYearRewardDropInfo id="19121001" dropId="191210" site="210" para2="1" itemId="2120107" count="50" isBind="1" appearType="1" validDate="0" isShow="0"/>
	<SevenYearRewardDropInfo id="19121101" dropId="191211" site="211" para2="0" itemId="212032" count="60" isBind="1" appearType="1" validDate="0" isShow="0"/>
	<SevenYearRewardDropInfo id="19121501" dropId="191215" site="215" para2="1" itemId="2120106" count="50" isBind="1" appearType="1" validDate="0" isShow="0"/>
	<SevenYearRewardDropInfo id="19121901" dropId="191219" site="219" para2="0" itemId="212033" count="60" isBind="1" appearType="1" validDate="0" isShow="0"/>
	<SevenYearRewardDropInfo id="19122001" dropId="191220" site="220" para2="1" itemId="6920001" count="100" isBind="1" appearType="1" validDate="0" isShow="0"/>
	<SevenYearRewardDropInfo id="19122301" dropId="191223" site="223" para2="0" itemId="6670012" count="2" isBind="1" appearType="1" validDate="0" isShow="0"/>
	<SevenYearRewardDropInfo id="19122501" dropId="191225" site="225" para2="1" itemId="21260569" count="1" isBind="1" appearType="1" validDate="0" isShow="0"/>
	<SevenYearRewardDropInfo id="19122701" dropId="191227" site="227" para2="0" itemId="208550" count="50" isBind="1" appearType="1" validDate="0" isShow="0"/>
	<SevenYearRewardDropInfo id="19123001" dropId="191230" site="230" para2="1" itemId="6260003" count="20" isBind="1" appearType="1" validDate="0" isShow="0"/>
	<SevenYearRewardDropInfo id="19123101" dropId="191231" site="231" para2="0" itemId="6670013" count="2" isBind="1" appearType="1" validDate="0" isShow="0"/>
	<SevenYearRewardDropInfo id="19123501" dropId="191235" site="235" para2="1" itemId="208550" count="50" isBind="1" appearType="1" validDate="0" isShow="0"/>
	<SevenYearRewardDropInfo id="19123901" dropId="191239" site="239" para2="0" itemId="6670014" count="2" isBind="1" appearType="1" validDate="0" isShow="0"/>
	<SevenYearRewardDropInfo id="19124001" dropId="191240" site="240" para2="1" itemId="208066" count="30" isBind="1" appearType="1" validDate="0" isShow="0"/>
	<SevenYearRewardDropInfo id="19124301" dropId="191243" site="243" para2="0" itemId="2183055" count="1" isBind="1" appearType="1" validDate="0" isShow="0"/>
	<SevenYearRewardDropInfo id="19124501" dropId="191245" site="245" para2="1" itemId="208500" count="200" isBind="1" appearType="1" validDate="0" isShow="0"/>
	<SevenYearRewardDropInfo id="19124701" dropId="191247" site="247" para2="0" itemId="208064" count="200" isBind="1" appearType="1" validDate="0" isShow="0"/>
	<SevenYearRewardDropInfo id="19125001" dropId="191250" site="250" para2="1" itemId="208067" count="30" isBind="1" appearType="1" validDate="0" isShow="0"/>
	<SevenYearRewardDropInfo id="19125101" dropId="191251" site="251" para2="0" itemId="212029" count="60" isBind="1" appearType="1" validDate="0" isShow="0"/>
	<SevenYearRewardDropInfo id="19125501" dropId="191255" site="255" para2="1" itemId="6920001" count="100" isBind="1" appearType="1" validDate="0" isShow="0"/>
	<SevenYearRewardDropInfo id="19125901" dropId="191259" site="259" para2="0" itemId="212030" count="60" isBind="1" appearType="1" validDate="0" isShow="0"/>
	<SevenYearRewardDropInfo id="19126001" dropId="191260" site="260" para2="1" itemId="21260418" count="3" isBind="1" appearType="1" validDate="0" isShow="0"/>
	<SevenYearRewardDropInfo id="19126301" dropId="191263" site="263" para2="0" itemId="6920001" count="180" isBind="1" appearType="1" validDate="0" isShow="0"/>
	<SevenYearRewardDropInfo id="19126501" dropId="191265" site="265" para2="1" itemId="208511" count="1" isBind="1" appearType="1" validDate="0" isShow="0"/>
	<SevenYearRewardDropInfo id="19126701" dropId="191267" site="267" para2="0" itemId="212031" count="60" isBind="1" appearType="1" validDate="0" isShow="0"/>
	<SevenYearRewardDropInfo id="19127001" dropId="191270" site="270" para2="1" itemId="2120107" count="50" isBind="1" appearType="1" validDate="0" isShow="0"/>
	<SevenYearRewardDropInfo id="19127101" dropId="191271" site="271" para2="0" itemId="6920001" count="190" isBind="1" appearType="1" validDate="0" isShow="0"/>
	<SevenYearRewardDropInfo id="19127501" dropId="191275" site="275" para2="1" itemId="2120106" count="50" isBind="1" appearType="1" validDate="0" isShow="0"/>
	<SevenYearRewardDropInfo id="19127901" dropId="191279" site="279" para2="0" itemId="6670011" count="2" isBind="1" appearType="1" validDate="0" isShow="0"/>
	<SevenYearRewardDropInfo id="19128001" dropId="191280" site="280" para2="1" itemId="208067" count="30" isBind="1" appearType="1" validDate="0" isShow="0"/>
	<SevenYearRewardDropInfo id="19128301" dropId="191283" site="283" para2="0" itemId="212033" count="60" isBind="1" appearType="1" validDate="0" isShow="0"/>
	<SevenYearRewardDropInfo id="19128501" dropId="191285" site="285" para2="1" itemId="208550" count="50" isBind="1" appearType="1" validDate="0" isShow="0"/>
	<SevenYearRewardDropInfo id="19128701" dropId="191287" site="287" para2="0" itemId="6670012" count="2" isBind="1" appearType="1" validDate="0" isShow="0"/>
	<SevenYearRewardDropInfo id="19129001" dropId="191290" site="290" para2="1" itemId="208066" count="30" isBind="1" appearType="1" validDate="0" isShow="0"/>
	<SevenYearRewardDropInfo id="19129101" dropId="191291" site="291" para2="0" itemId="208550" count="50" isBind="1" appearType="1" validDate="0" isShow="0"/>
	<SevenYearRewardDropInfo id="19129501" dropId="191295" site="295" para2="1" itemId="208500" count="200" isBind="1" appearType="1" validDate="0" isShow="0"/>
	<SevenYearRewardDropInfo id="19129901" dropId="191299" site="299" para2="0" itemId="212028" count="500" isBind="1" appearType="1" validDate="0" isShow="0"/>
	<SevenYearRewardDropInfo id="19130001" dropId="191300" site="300" para2="1" itemId="1116433" count="1" isBind="1" appearType="1" validDate="0" isShow="0"/>
	<SevenYearRewardDropInfo id="19130301" dropId="191303" site="303" para2="0" itemId="6670014" count="2" isBind="1" appearType="1" validDate="0" isShow="0"/>
	<SevenYearRewardDropInfo id="19130501" dropId="191305" site="305" para2="1" itemId="208511" count="1" isBind="1" appearType="1" validDate="0" isShow="0"/>
	<SevenYearRewardDropInfo id="19130701" dropId="191307" site="307" para2="0" itemId="2183058" count="1" isBind="1" appearType="1" validDate="0" isShow="0"/>
	<SevenYearRewardDropInfo id="19131001" dropId="191310" site="310" para2="1" itemId="208500" count="300" isBind="1" appearType="1" validDate="0" isShow="0"/>
	<SevenYearRewardDropInfo id="19131101" dropId="191311" site="311" para2="0" itemId="208064" count="300" isBind="1" appearType="1" validDate="0" isShow="0"/>
	<SevenYearRewardDropInfo id="19131501" dropId="191315" site="315" para2="1" itemId="6920001" count="100" isBind="1" appearType="1" validDate="0" isShow="0"/>
	<SevenYearRewardDropInfo id="19131901" dropId="191319" site="319" para2="0" itemId="6920001" count="200" isBind="1" appearType="1" validDate="0" isShow="0"/>
	<SevenYearRewardDropInfo id="19132001" dropId="191320" site="320" para2="1" itemId="208063" count="100" isBind="1" appearType="1" validDate="0" isShow="0"/>
	<SevenYearRewardDropInfo id="19132301" dropId="191323" site="323" para2="0" itemId="212030" count="50" isBind="1" appearType="1" validDate="0" isShow="0"/>
	<SevenYearRewardDropInfo id="19132501" dropId="191325" site="325" para2="1" itemId="21260418" count="4" isBind="1" appearType="1" validDate="0" isShow="0"/>
	<SevenYearRewardDropInfo id="19132701" dropId="191327" site="327" para2="0" itemId="6920001" count="210" isBind="1" appearType="1" validDate="0" isShow="0"/>
	<SevenYearRewardDropInfo id="19133001" dropId="191330" site="330" para2="1" itemId="2120107" count="50" isBind="1" appearType="1" validDate="0" isShow="0"/>
	<SevenYearRewardDropInfo id="19133101" dropId="191331" site="331" para2="0" itemId="212031" count="50" isBind="1" appearType="1" validDate="0" isShow="0"/>
	<SevenYearRewardDropInfo id="19133501" dropId="191335" site="335" para2="1" itemId="2120106" count="50" isBind="1" appearType="1" validDate="0" isShow="0"/>
	<SevenYearRewardDropInfo id="19133901" dropId="191339" site="339" para2="0" itemId="212032" count="50" isBind="1" appearType="1" validDate="0" isShow="0"/>
	<SevenYearRewardDropInfo id="19134001" dropId="191340" site="340" para2="1" itemId="21260569" count="1" isBind="1" appearType="1" validDate="0" isShow="0"/>
	<SevenYearRewardDropInfo id="19134301" dropId="191343" site="343" para2="0" itemId="6670011" count="2" isBind="1" appearType="1" validDate="0" isShow="0"/>
	<SevenYearRewardDropInfo id="19134501" dropId="191345" site="345" para2="1" itemId="208500" count="300" isBind="1" appearType="1" validDate="0" isShow="0"/>
	<SevenYearRewardDropInfo id="19134701" dropId="191347" site="347" para2="0" itemId="212033" count="50" isBind="1" appearType="1" validDate="0" isShow="0"/>
	<SevenYearRewardDropInfo id="19135001" dropId="191350" site="350" para2="1" itemId="1126433" count="1" isBind="1" appearType="1" validDate="0" isShow="0"/>
	<SevenYearRewardDropInfo id="19135101" dropId="191351" site="351" para2="0" itemId="6670012" count="2" isBind="1" appearType="1" validDate="0" isShow="0"/>
	<SevenYearRewardDropInfo id="19135501" dropId="191355" site="355" para2="1" itemId="208066" count="30" isBind="1" appearType="1" validDate="0" isShow="0"/>
	<SevenYearRewardDropInfo id="19135901" dropId="191359" site="359" para2="0" itemId="6670013" count="2" isBind="1" appearType="1" validDate="0" isShow="0"/>
	<SevenYearRewardDropInfo id="19136001" dropId="191360" site="360" para2="1" itemId="208550" count="50" isBind="1" appearType="1" validDate="0" isShow="0"/>
	<SevenYearRewardDropInfo id="19136301" dropId="191363" site="363" para2="0" itemId="212028" count="300" isBind="1" appearType="1" validDate="0" isShow="0"/>
	<SevenYearRewardDropInfo id="19136501" dropId="191365" site="365" para2="1" itemId="208500" count="300" isBind="1" appearType="1" validDate="0" isShow="0"/>
	<SevenYearRewardDropInfo id="19136701" dropId="191367" site="367" para2="0" itemId="6670014" count="2" isBind="1" appearType="1" validDate="0" isShow="0"/>
	<SevenYearRewardDropInfo id="19137001" dropId="191370" site="370" para2="1" itemId="208511" count="1" isBind="1" appearType="1" validDate="0" isShow="0"/>
	<SevenYearRewardDropInfo id="19137101" dropId="191371" site="371" para2="0" itemId="2183062" count="1" isBind="1" appearType="1" validDate="0" isShow="0"/>
	<SevenYearRewardDropInfo id="19137501" dropId="191375" site="375" para2="1" itemId="208521" count="1" isBind="1" appearType="1" validDate="0" isShow="0"/>
	<SevenYearRewardDropInfo id="19137901" dropId="191379" site="379" para2="0" itemId="212029" count="60" isBind="1" appearType="1" validDate="0" isShow="0"/>
	<SevenYearRewardDropInfo id="19138001" dropId="191380" site="380" para2="1" itemId="6920001" count="100" isBind="1" appearType="1" validDate="0" isShow="0"/>
	<SevenYearRewardDropInfo id="19138301" dropId="191383" site="383" para2="0" itemId="6920001" count="230" isBind="1" appearType="1" validDate="0" isShow="0"/>
	<SevenYearRewardDropInfo id="19138501" dropId="191385" site="385" para2="1" itemId="2120107" count="50" isBind="1" appearType="1" validDate="0" isShow="0"/>
	<SevenYearRewardDropInfo id="19138701" dropId="191387" site="387" para2="0" itemId="212030" count="60" isBind="1" appearType="1" validDate="0" isShow="0"/>
	<SevenYearRewardDropInfo id="19139001" dropId="191390" site="390" para2="1" itemId="2120106" count="50" isBind="1" appearType="1" validDate="0" isShow="0"/>
	<SevenYearRewardDropInfo id="19139101" dropId="191391" site="391" para2="0" itemId="6920001" count="240" isBind="1" appearType="1" validDate="0" isShow="0"/>
	<SevenYearRewardDropInfo id="19139501" dropId="191395" site="395" para2="1" itemId="6260003" count="20" isBind="1" appearType="1" validDate="0" isShow="0"/>
	<SevenYearRewardDropInfo id="19139901" dropId="191399" site="399" para2="0" itemId="6920001" count="250" isBind="1" appearType="1" validDate="0" isShow="0"/>
	<SevenYearRewardDropInfo id="19140001" dropId="191400" site="400" para2="1" itemId="1096433" count="1" isBind="1" appearType="1" validDate="0" isShow="0"/>
	<SevenYearRewardDropInfo id="19140301" dropId="191403" site="403" para2="0" itemId="212032" count="60" isBind="1" appearType="1" validDate="0" isShow="0"/>
	<SevenYearRewardDropInfo id="19140501" dropId="191405" site="405" para2="1" itemId="208511" count="1" isBind="1" appearType="1" validDate="0" isShow="0"/>
	<SevenYearRewardDropInfo id="19140701" dropId="191407" site="407" para2="0" itemId="6670011" count="2" isBind="1" appearType="1" validDate="0" isShow="0"/>
	<SevenYearRewardDropInfo id="19141001" dropId="191410" site="410" para2="1" itemId="5010001" count="100" isBind="1" appearType="1" validDate="0" isShow="0"/>
	<SevenYearRewardDropInfo id="19141101" dropId="191411" site="411" para2="0" itemId="212033" count="60" isBind="1" appearType="1" validDate="0" isShow="0"/>
	<SevenYearRewardDropInfo id="19141501" dropId="191415" site="415" para2="1" itemId="208550" count="50" isBind="1" appearType="1" validDate="0" isShow="0"/>
	<SevenYearRewardDropInfo id="19141901" dropId="191419" site="419" para2="0" itemId="208550" count="100" isBind="1" appearType="1" validDate="0" isShow="0"/>
	<SevenYearRewardDropInfo id="19142001" dropId="191420" site="420" para2="1" itemId="21260418" count="5" isBind="1" appearType="1" validDate="0" isShow="0"/>
	<SevenYearRewardDropInfo id="19142301" dropId="191423" site="423" para2="0" itemId="6670013" count="2" isBind="1" appearType="1" validDate="0" isShow="0"/>
	<SevenYearRewardDropInfo id="19142501" dropId="191425" site="425" para2="1" itemId="21260569" count="1" isBind="1" appearType="1" validDate="0" isShow="0"/>
	<SevenYearRewardDropInfo id="19142701" dropId="191427" site="427" para2="0" itemId="212028" count="500" isBind="1" appearType="1" validDate="0" isShow="0"/>
	<SevenYearRewardDropInfo id="19143001" dropId="191430" site="430" para2="1" itemId="6920001" count="150" isBind="1" appearType="1" validDate="0" isShow="0"/>
	<SevenYearRewardDropInfo id="19143101" dropId="191431" site="431" para2="0" itemId="6670014" count="2" isBind="1" appearType="1" validDate="0" isShow="0"/>
	<SevenYearRewardDropInfo id="19143501" dropId="191435" site="435" para2="1" itemId="208521" count="1" isBind="1" appearType="1" validDate="0" isShow="0"/>
	<SevenYearRewardDropInfo id="19143901" dropId="191439" site="439" para2="0" itemId="208064" count="600" isBind="1" appearType="1" validDate="0" isShow="0"/>
	<SevenYearRewardDropInfo id="19144001" dropId="191440" site="440" para2="1" itemId="208511" count="1" isBind="1" appearType="1" validDate="0" isShow="0"/>
	<SevenYearRewardDropInfo id="19144301" dropId="191443" site="443" para2="0" itemId="212029" count="60" isBind="1" appearType="1" validDate="0" isShow="0"/>
	<SevenYearRewardDropInfo id="19144501" dropId="191445" site="445" para2="1" itemId="2120107" count="100" isBind="1" appearType="1" validDate="0" isShow="0"/>
	<SevenYearRewardDropInfo id="19144701" dropId="191447" site="447" para2="0" itemId="6920001" count="300" isBind="1" appearType="1" validDate="0" isShow="0"/>
	<SevenYearRewardDropInfo id="19145001" dropId="191450" site="450" para2="1" itemId="2120106" count="100" isBind="1" appearType="1" validDate="0" isShow="0"/>
	<SevenYearRewardDropInfo id="19145101" dropId="191451" site="451" para2="0" itemId="212030" count="60" isBind="1" appearType="1" validDate="0" isShow="0"/>
	<SevenYearRewardDropInfo id="19145501" dropId="191455" site="455" para2="1" itemId="208550" count="50" isBind="1" appearType="1" validDate="0" isShow="0"/>
	<SevenYearRewardDropInfo id="19145901" dropId="191459" site="459" para2="0" itemId="212031" count="60" isBind="1" appearType="1" validDate="0" isShow="0"/>
	<SevenYearRewardDropInfo id="19146001" dropId="191460" site="460" para2="1" itemId="6920001" count="150" isBind="1" appearType="1" validDate="0" isShow="0"/>
	<SevenYearRewardDropInfo id="19146301" dropId="191463" site="463" para2="0" itemId="6920001" count="400" isBind="1" appearType="1" validDate="0" isShow="0"/>
	<SevenYearRewardDropInfo id="19146501" dropId="191465" site="465" para2="1" itemId="208521" count="1" isBind="1" appearType="1" validDate="0" isShow="0"/>
	<SevenYearRewardDropInfo id="19146701" dropId="191467" site="467" para2="0" itemId="212032" count="60" isBind="1" appearType="1" validDate="0" isShow="0"/>
	<SevenYearRewardDropInfo id="19147001" dropId="191470" site="470" para2="1" itemId="208511" count="2" isBind="1" appearType="1" validDate="0" isShow="0"/>
	<SevenYearRewardDropInfo id="19147101" dropId="191471" site="471" para2="0" itemId="6670011" count="2" isBind="1" appearType="1" validDate="0" isShow="0"/>
	<SevenYearRewardDropInfo id="19147501" dropId="191475" site="475" para2="1" itemId="6920001" count="200" isBind="1" appearType="1" validDate="0" isShow="0"/>
	<SevenYearRewardDropInfo id="19147901" dropId="191479" site="479" para2="0" itemId="6670012" count="2" isBind="1" appearType="1" validDate="0" isShow="0"/>
	<SevenYearRewardDropInfo id="19148001" dropId="191480" site="480" para2="1" itemId="6930001" count="5" isBind="1" appearType="1" validDate="0" isShow="0"/>
	<SevenYearRewardDropInfo id="19148301" dropId="191483" site="483" para2="0" itemId="208550" count="100" isBind="1" appearType="1" validDate="0" isShow="0"/>
	<SevenYearRewardDropInfo id="19148501" dropId="191485" site="485" para2="1" itemId="6260003" count="50" isBind="1" appearType="1" validDate="0" isShow="0"/>
	<SevenYearRewardDropInfo id="19148701" dropId="191487" site="487" para2="0" itemId="6670013" count="2" isBind="1" appearType="1" validDate="0" isShow="0"/>
	<SevenYearRewardDropInfo id="19149001" dropId="191490" site="490" para2="1" itemId="208500" count="400" isBind="1" appearType="1" validDate="0" isShow="0"/>
	<SevenYearRewardDropInfo id="19149101" dropId="191491" site="491" para2="0" itemId="212028" count="500" isBind="1" appearType="1" validDate="0" isShow="0"/>
	<SevenYearRewardDropInfo id="19149501" dropId="191495" site="495" para2="1" itemId="208521" count="2" isBind="1" appearType="1" validDate="0" isShow="0"/>
	<SevenYearRewardDropInfo id="19150001" dropId="191500" site="500" para2="1" itemId="2183134" count="1" isBind="1" appearType="1" validDate="0" isShow="0"/>
</SevenYearRewardDrop>